<?xml version="1.0" encoding="UTF-8" ?><tv date="20260423">
<channel id="TV3Plus.dk@SD"><display-name>3 Plus Danmark</display-name><icon src="https://i.imgur.com/pj9jZHP.png"/><url>https://tv.nu</url></channel>
<channel id="3sat.de@SD"><display-name>3sat</display-name><icon src="https://upload.wikimedia.org/wikipedia/commons/thumb/8/81/3sat_2019.svg/960px-3sat_2019.svg.png"/><url>https://tv.nu</url></channel>
<channel id="AdultChannel.uk@SD"><display-name>Adult Channel</display-name><icon src="https://i.imgur.com/CLBDM6g.png"/><url>https://tv.nu</url></channel>
<channel id="adult-channel-nightly"><display-name>Adult Channel Nightly</display-name><url>https://tv.nu</url></channel>
<channel id="AlJazeera.qa@English"><display-name>Al Jazeera English</display-name><icon src="https://upload.wikimedia.org/wikipedia/ms/thumb/f/f2/Aljazeera_eng.svg/500px-Aljazeera_eng.svg.png"/><url>https://tv.nu</url></channel>
<channel id="AnimalPlanetNordic.uk@SD"><display-name>Animal Planet</display-name><icon src="https://upload.wikimedia.org/wikipedia/commons/thumb/2/20/2018_Animal_Planet_logo.svg/960px-2018_Animal_Planet_logo.svg.png"/><url>https://tv.nu</url></channel>
<channel id="arte.fr@SD"><display-name>ARTE</display-name><icon src="https://i.imgur.com/ecXMjNl.png"/><url>https://tv.nu</url></channel>
<channel id="ATGLive.se@SD"><display-name>ATG Live</display-name><icon src="https://i.imgur.com/bPWFXkL.png"/><url>https://tv.nu</url></channel>
<channel id="AxessTV.se@SD"><display-name>Axess TV</display-name><icon src="https://i.imgur.com/cKM7uSR.png"/><url>https://tv.nu</url></channel>
<channel id="BBCEarth.uk@Nordic"><display-name>BBC Earth</display-name><icon src="https://i.imgur.com/nGSsUd4.png"/><url>https://tv.nu</url></channel>
<channel id="bbc-news"><display-name>BBC News</display-name><url>https://tv.nu</url></channel>
<channel id="BBCNordic.uk@SD"><display-name>BBC Nordic</display-name><icon src="https://i.imgur.com/pC4pZuz.jpg"/><url>https://tv.nu</url></channel>
<channel id="bloomberg-tv-hd-uk"><display-name>Bloomberg TV HD (UK)</display-name><url>https://tv.nu</url></channel>
<channel id="BrazzersTVEurope.us@SD"><display-name>BraZZers TV Plus</display-name><icon src="https://i.imgur.com/95nP0Pb.png"/><url>https://tv.nu</url></channel>
<channel id="SFkanalen.se@SD"><display-name>SF-Kanalen</display-name><icon src="https://i.imgur.com/YpnN63k.png"/><url>https://tv.nu</url></channel>
<channel id="cartoon-network"><display-name>Cartoon Network</display-name><url>https://tv.nu</url></channel>
<channel id="CartoonitoWesternEurope.uk@Sweden"><display-name>Cartoonito</display-name><icon src="https://i.imgur.com/9MrzLb1.png"/><url>https://tv.nu</url></channel>
<channel id="cbs-reality-mena"><display-name>CBS Reality MENA</display-name><url>https://tv.nu</url></channel>
<channel id="china-global-television-network"><display-name>China Global Television Network</display-name><url>https://tv.nu</url></channel>
<channel id="CGTNDocumentary.cn@SD"><display-name>China Global Television Network 9 Documentary</display-name><icon src="https://i.imgur.com/JHv0WxM.png"/><url>https://tv.nu</url></channel>
<channel id="ClubMTVEurope.uk@SD"><display-name>Club MTV</display-name><icon src="https://i.imgur.com/FD6eQI3.png"/><url>https://tv.nu</url></channel>
<channel id="CNBCEurope.uk@SD"><display-name>CNBC</display-name><icon src="https://upload.wikimedia.org/wikipedia/commons/b/bc/CNBC_2025.svg"/><url>https://tv.nu</url></channel>
<channel id="CNNInternational.us@MENA"><display-name>CNN International</display-name><icon src="https://dtil.tmsimg.com/assets/s157679_ld_h15_aa.png?lock=720x540"/><url>https://tv.nu</url></channel>
<channel id="CuriosityChannel.us@SD"><display-name>CuriosityStream</display-name><icon src="https://i.imgur.com/K0kZMYo.png"/><url>https://tv.nu</url></channel>
<channel id="DasErste.de@SD"><display-name>Das Erste</display-name><icon src="https://upload.wikimedia.org/wikipedia/commons/thumb/d/d1/ARD_Dachmarke_2014.svg/960px-ARD_Dachmarke_2014.svg.png"/><url>https://tv.nu</url></channel>
<channel id="DiscoveryChannel.se@SD"><display-name>Discovery Channel</display-name><icon src="https://i.imgur.com/7pmvDqg.png"/><url>https://tv.nu</url></channel>
<channel id="DiscoveryPlusExtra1.se@SD"><display-name>Discovery+ Extra 1</display-name><icon src="https://i.imgur.com/O9JdSXT.png"/><url>https://tv.nu</url></channel>
<channel id="DiscoveryPlusExtra2.se@SD"><display-name>Discovery+ Extra 2</display-name><icon src="https://i.imgur.com/SiPFp5T.png"/><url>https://tv.nu</url></channel>
<channel id="DiscoveryPlusExtra3.se@SD"><display-name>Discovery+ Extra 3</display-name><icon src="https://i.imgur.com/u4UlDGk.png"/><url>https://tv.nu</url></channel>
<channel id="DiscoveryPlusExtra4.se@SD"><display-name>Discovery+ Extra 4</display-name><icon src="https://i.imgur.com/u4UlDGk.png"/><url>https://tv.nu</url></channel>
<channel id="DiscoveryPlusExtra5.se@SD"><display-name>Discovery+ Extra 5</display-name><icon src="https://i.imgur.com/u4UlDGk.png"/><url>https://tv.nu</url></channel>
<channel id="DiscoveryPlusExtra6.se@SD"><display-name>Discovery+ Extra 6</display-name><icon src="https://i.imgur.com/u4UlDGk.png"/><url>https://tv.nu</url></channel>
<channel id="DiscoveryPlusExtra7.se@SD"><display-name>Discovery+ Extra 7</display-name><icon src="https://i.imgur.com/u4UlDGk.png"/><url>https://tv.nu</url></channel>
<channel id="DiscoveryPlusExtra8.se@SD"><display-name>Discovery+ Extra 8</display-name><icon src="https://i.imgur.com/u4UlDGk.png"/><url>https://tv.nu</url></channel>
<channel id="DiscoveryScienceEurope.uk@UKHD"><display-name>Discovery Science</display-name><icon src="https://upload.wikimedia.org/wikipedia/commons/thumb/2/29/Discovery_Science_2017_Logo.svg/960px-Discovery_Science_2017_Logo.svg.png"/><url>https://tv.nu</url></channel>
<channel id="DisneyChannelScandinavia.uk@SD"><display-name>Disney Channel</display-name><icon src="https://upload.wikimedia.org/wikipedia/commons/3/3d/2022_Disney_Channel_logo.svg"/><url>https://tv.nu</url></channel>
<channel id="DisneyJuniorScandinavia.uk@SD"><display-name>Disney Junior</display-name><icon src="https://upload.wikimedia.org/wikipedia/commons/e/e3/2024_Disney_Jr._Logo.svg"/><url>https://tv.nu</url></channel>
<channel id="disney-junior-lang-tabla"><display-name>Disney Junior (lång tablå)</display-name><url>https://tv.nu</url></channel>
<channel id="StingrayDJAZZ.ca@SD"><display-name>Djazz HD</display-name><icon src="https://upload.wikimedia.org/wikipedia/commons/thumb/1/14/Stingray_Djazz.png/960px-Stingray_Djazz.png"/><url>https://tv.nu</url></channel>
<channel id="dk4.dk@SD"><display-name>DK4</display-name><icon src="https://i.imgur.com/eTZ1qdk.png"/><url>https://tv.nu</url></channel>
<channel id="dk4.dk@HD"><display-name>DK4 HD</display-name><icon src="https://i.imgur.com/eTZ1qdk.png"/><url>https://tv.nu</url></channel>
<channel id="DMAX.de@SD"><display-name>DMAX</display-name><icon src="https://upload.wikimedia.org/wikipedia/commons/thumb/9/98/DMAX_BLACK.svg/960px-DMAX_BLACK.svg.png"/><url>https://tv.nu</url></channel>
<channel id="DR1.dk@SD"><display-name>DR1</display-name><icon src="https://i.imgur.com/OETzsOI.png"/><url>https://tv.nu</url></channel>
<channel id="DR2.dk@SD"><display-name>DR2</display-name><icon src="https://i.imgur.com/7bYtukP.png"/><url>https://tv.nu</url></channel>
<channel id="DR3.dk@SD"><display-name>DR3</display-name><icon src="https://upload.wikimedia.org/wikipedia/commons/thumb/e/ee/DR3_Logo_2020.svg/960px-DR3_Logo_2020.svg.png"/><url>https://tv.nu</url></channel>
<channel id="DRK.dk@SD"><display-name>DR K</display-name><icon src="https://i.imgur.com/hzVLK9Y.png"/><url>https://tv.nu</url></channel>
<channel id="DRRamasjang.dk@SD"><display-name>DR Ramasjang</display-name><icon src="https://upload.wikimedia.org/wikipedia/en/thumb/8/82/DR_Ramasjang_2020.svg/960px-DR_Ramasjang_2020.svg.png"/><url>https://tv.nu</url></channel>
<channel id="DRUltra.dk@SD"><display-name>DR Ultra</display-name><icon src="https://upload.wikimedia.org/wikipedia/commons/thumb/a/ae/DR_Ultra_Logo_2020.svg/960px-DR_Ultra_Logo_2020.svg.png"/><url>https://tv.nu</url></channel>
<channel id="dw"><display-name>DW</display-name><url>https://tv.nu</url></channel>
<channel id="EEurope.nl@SD"><display-name>E!</display-name><icon src="https://i.imgur.com/TWFDkap.png"/><url>https://tv.nu</url></channel>
<channel id="eSports1.de@SD"><display-name>eSportsone</display-name><icon src="https://i.imgur.com/282zLCo.png"/><url>https://tv.nu</url></channel>
<channel id="EuronewsEnglish.fr@SD"><display-name>Euro News</display-name><icon src="https://a.jsrdn.com/hls/22886/euronews/extras/1080_logo.png"/><url>https://tv.nu</url></channel>
<channel id="Eurosport1.fr@France"><display-name>Eurosport 1</display-name><icon src="https://i.imgur.com/olQJgm7.png"/><url>https://tv.nu</url></channel>
<channel id="Eurosport2.fr@France"><display-name>Eurosport 2</display-name><icon src="https://i.imgur.com/f56dHgR.png"/><url>https://tv.nu</url></channel>
<channel id="ExtremeSportsChannel.nl@SD"><display-name>Extreme Sports Channel</display-name><icon src="https://i.imgur.com/m7IC01U.png"/><url>https://tv.nu</url></channel>
<channel id="FightSports.us@SD"><display-name>Fight Sports</display-name><icon src="https://i.imgur.com/nV55veq.png"/><url>https://tv.nu</url></channel>
<channel id="France2.fr@SD"><display-name>France 2</display-name><icon src="https://upload.wikimedia.org/wikipedia/commons/thumb/5/53/France_2_2018.svg/960px-France_2_2018.svg.png"/><url>https://tv.nu</url></channel>
<channel id="France24.fr@EnglishHD"><display-name>France 24 English HD</display-name><icon src="https://dtil.tmsimg.com/assets/s159111_ld_h15_aa.png?lock=720x540"/><url>https://tv.nu</url></channel>
<channel id="FashionTVEurope.fr@SD"><display-name>FTV</display-name><icon src="https://upload.wikimedia.org/wikipedia/commons/thumb/7/7a/Fashion_TV_logo.svg/960px-Fashion_TV_logo.svg.png"/><url>https://tv.nu</url></channel>
<channel id="FUELTV.at@SD"><display-name>FUEL TV</display-name><url>https://tv.nu</url></channel>
<channel id="GINXTV.uk@SD"><display-name>GINX eSports TV</display-name><icon src="https://i.imgur.com/diw20TN.png"/><url>https://tv.nu</url></channel>
<channel id="GODTV.uk@SD"><display-name>GOD TV</display-name><icon src="https://i.imgur.com/hW4g2oe.png"/><url>https://tv.nu</url></channel>
<channel id="Godare.se@SD"><display-name>Godare</display-name><icon src="https://i.imgur.com/F0k9nIc.png"/><url>https://tv.nu</url></channel>
<channel id="History2Nordic.us@SD"><display-name>H2</display-name><icon src="https://upload.wikimedia.org/wikipedia/commons/thumb/c/c9/History2_logo_%282022%29.svg/500px-History2_logo_%282022%29.svg.png"/><url>https://tv.nu</url></channel>
<channel id="HighTV3D.us@SD"><display-name>High TV 3D</display-name><icon src="https://i.imgur.com/isohJ5Q.png"/><url>https://tv.nu</url></channel>
<channel id="History.se@HD"><display-name>History HD</display-name><icon src="https://upload.wikimedia.org/wikipedia/commons/thumb/0/01/History_%282021%29.svg/500px-History_%282021%29.svg.png"/><url>https://tv.nu</url></channel>
<channel id="history-hd-internationell"><display-name>History HD (Internationell)</display-name><url>https://tv.nu</url></channel>
<channel id="SkyHistory.uk@SD"><display-name>History (UK)</display-name><icon src="https://d2n0069hmnqmmx.cloudfront.net/epgdata/1.0/newchanlogos/512/512/skychb1875.png"/><url>https://tv.nu</url></channel>
<channel id="HorseCountryTV.uk@SD"><display-name>Horse &amp; Country TV</display-name><icon src="https://i.imgur.com/1x6zYZr.png"/><url>https://tv.nu</url></channel>
<channel id="HRT1.hr@SD"><display-name>HRT1</display-name><icon src="https://upload.wikimedia.org/wikipedia/commons/1/1f/HRT1-logo.png"/><url>https://tv.nu</url></channel>
<channel id="HustlerHD.nl@SD"><display-name>Hustler TV</display-name><icon src="https://i.imgur.com/41Ej2io.png"/><url>https://tv.nu</url></channel>
<channel id="InvestigationDiscovery.se@SD"><display-name>Investigation Discovery</display-name><icon src="https://upload.wikimedia.org/wikipedia/commons/thumb/3/35/InvestigationDiscoveryLogo2020.svg/960px-InvestigationDiscoveryLogo2020.svg.png"/><url>https://tv.nu</url></channel>
<channel id="Kanal4.dk@SD"><display-name>Kanal 4</display-name><icon src="https://upload.wikimedia.org/wikipedia/commons/thumb/5/50/Kanal_4_Logo_2024.svg/960px-Kanal_4_Logo_2024.svg.png"/><url>https://tv.nu</url></channel>
<channel id="Kanal5.se@SD"><display-name>Kanal 5</display-name><icon src="https://upload.wikimedia.org/wikipedia/commons/d/d3/Kanal_5_%26_TV5_Logo_2024.svg"/><url>https://tv.nu</url></channel>
<channel id="Kanal5.dk@SD"><display-name>Kanal 5 Danmark</display-name><icon src="https://upload.wikimedia.org/wikipedia/commons/thumb/d/d3/Kanal_5_%26_TV5_Logo_2024.svg/960px-Kanal_5_%26_TV5_Logo_2024.svg.png"/><url>https://tv.nu</url></channel>
<channel id="Kanal9.se@SD"><display-name>Kanal 9</display-name><icon src="https://upload.wikimedia.org/wikipedia/commons/d/df/Kanal_9_Logo_2024.svg"/><url>https://tv.nu</url></channel>
<channel id="Kanal10.se@SD"><display-name>Kanal 10</display-name><icon src="https://i.imgur.com/FGGPANK.png"/><url>https://tv.nu</url></channel>
<channel id="Kanal11.se@SD"><display-name>Kanal 11</display-name><icon src="https://upload.wikimedia.org/wikipedia/commons/thumb/e/e7/Kanal_11_Logo_2024.svg/960px-Kanal_11_Logo_2024.svg.png"/><url>https://tv.nu</url></channel>
<channel id="Kunskapskanalen.se@SD"><display-name>Kunskapskanalen</display-name><icon src="https://upload.wikimedia.org/wikipedia/commons/thumb/3/37/Kunskapskanalen_2017.svg/960px-Kunskapskanalen_2017.svg.png"/><url>https://tv.nu</url></channel>
<channel id="LoveNature.ca@4K"><display-name>Love Nature 4K UHD</display-name><icon src="https://tv.lovenature.com/wp-content/uploads/2024/10/LoveNature2024_Logo_full_colour-copy.png"/><url>https://tv.nu</url></channel>
<channel id="Mezzo.fr@SD"><display-name>Mezzo</display-name><icon src="https://i.imgur.com/auNdGeW.png"/><url>https://tv.nu</url></channel>
<channel id="MezzoLive.fr@SD"><display-name>Mezzo Live</display-name><icon src="https://i.imgur.com/H9ytKPN.png"/><url>https://tv.nu</url></channel>
<channel id="mitteldeutscher-rundfunk"><display-name>Mitteldeutscher Rundfunk (MDF)</display-name><url>https://tv.nu</url></channel>
<channel id="Motorvision.de@SD"><display-name>Motorvision TV</display-name><icon src="https://i.imgur.com/v4kj8pI.png"/><url>https://tv.nu</url></channel>
<channel id="MTVGlobal.uk@SD"><display-name>MTV</display-name><icon src="https://i.imgur.com/n2BoU7Q.png"/><url>https://tv.nu</url></channel>
<channel id="MTV3.fi@SD"><display-name>MTV3</display-name><icon src="https://i.imgur.com/C5rQbBM.png"/><url>https://tv.nu</url></channel>
<channel id="mtv-00s-europe"><display-name>MTV 00s Europe</display-name><url>https://tv.nu</url></channel>
<channel id="MTV80s.uk@SD"><display-name>MTV 80s</display-name><icon src="https://i.imgur.com/N9e5hv5.png"/><url>https://tv.nu</url></channel>
<channel id="MTV90s.uk@SD"><display-name>MTV 90s</display-name><icon src="https://i.imgur.com/au5zhwP.png"/><url>https://tv.nu</url></channel>
<channel id="MTVAitio.se@SD"><display-name>MTV Aitio</display-name><icon src="https://i.imgur.com/jRXC7oh.png"/><url>https://tv.nu</url></channel>
<channel id="MTVHitsEurope.uk@SD"><display-name>MTV Hits</display-name><icon src="https://i.imgur.com/zNscEST.png"/><url>https://tv.nu</url></channel>
<channel id="MTVLive.uk@SD"><display-name>MTV Live HD</display-name><icon src="https://upload.wikimedia.org/wikipedia/commons/3/30/MTV_Live_2021_logo.svg"/><url>https://tv.nu</url></channel>
<channel id="MTVViihde.se@SD"><display-name>MTV Viihde</display-name><icon src="https://i.imgur.com/gW2qMCs.png"/><url>https://tv.nu</url></channel>
<channel id="NationalGeographic.se@SD"><display-name>National Geographic</display-name><icon src="https://upload.wikimedia.org/wikipedia/commons/thumb/f/fc/Natgeologo.svg/960px-Natgeologo.svg.png"/><url>https://tv.nu</url></channel>
<channel id="national-geographic-3"><display-name>National Geographic (International)</display-name><url>https://tv.nu</url></channel>
<channel id="national-geographic-hd-3"><display-name>National Geographic HD</display-name><url>https://tv.nu</url></channel>
<channel id="national-geographic-hd-30242"><display-name>National Geographic HD</display-name><url>https://tv.nu</url></channel>
<channel id="NationalGeographicWild.se@SD"><display-name>National Geographic Wild</display-name><icon src="https://i.imgur.com/MFeyj6q.png"/><url>https://tv.nu</url></channel>
<channel id="NauticalChannel.it@SD"><display-name>Nautical Channel</display-name><icon src="https://i.imgur.com/2ByDyzL.png"/><url>https://tv.nu</url></channel>
<channel id="Nelonen.fi@SD"><display-name>Nelonen</display-name><icon src="https://i.imgur.com/BFbCyfY.png"/><url>https://tv.nu</url></channel>
<channel id="NFLNetwork.us@SD"><display-name>NFL Network</display-name><icon src="https://upload.wikimedia.org/wikipedia/en/thumb/8/8f/NFL_Network_logo.svg/960px-NFL_Network_logo.svg.png"/><url>https://tv.nu</url></channel>
<channel id="NHKWorldJapan.jp@SD"><display-name>NHK World Europe</display-name><icon src="https://jiotvimages.cdn.jio.com/dare_images/images/NHK_World_Japan.png"/><url>https://tv.nu</url></channel>
<channel id="NickJrScandinavia.nl@SD"><display-name>Nick JR</display-name><icon src="https://upload.wikimedia.org/wikipedia/commons/thumb/c/c5/Nick_Jr._logo_2023_(outline).svg/960px-Nick_Jr._logo_2023_(outline).svg.png"/><url>https://tv.nu</url></channel>
<channel id="nick-jr-lang-tabla"><display-name>Nick JR (lång tablå)</display-name><url>https://tv.nu</url></channel>
<channel id="NickelodeonScandinavia.nl@SD"><display-name>Nickelodeon</display-name><icon src="https://upload.wikimedia.org/wikipedia/commons/thumb/7/7a/Nickelodeon_2009_logo.svg/960px-Nickelodeon_2009_logo.svg.png"/><url>https://tv.nu</url></channel>
<channel id="NicktoonsScandinavia.nl@SD"><display-name>Nicktoons</display-name><icon src="https://upload.wikimedia.org/wikipedia/commons/d/d8/Nicktoons_UK_Logo_2014.png"/><url>https://tv.nu</url></channel>
<channel id="NRK1.no@SD"><display-name>NRK1</display-name><icon src="https://i.imgur.com/9tj8ds7.png"/><url>https://tv.nu</url></channel>
<channel id="NRK2.no@SD"><display-name>NRK2</display-name><icon src="https://i.imgur.com/SiAdoK9.png"/><url>https://tv.nu</url></channel>
<channel id="NRK3.no@SD"><display-name>NRK3</display-name><icon src="https://i.imgur.com/TNhV2I7.png"/><url>https://tv.nu</url></channel>
<channel id="NRKSuperNRK3.no@HD"><display-name>NRK Super / NRK3 HD</display-name><icon src="https://i.imgur.com/q5mpbzD.png"/><url>https://tv.nu</url></channel>
<channel id="OUTtv.nl@SD"><display-name>OUTtv</display-name><icon src="https://i.imgur.com/QlUWNSU.png"/><url>https://tv.nu</url></channel>
<channel id="PenthouseHD1.us@SD"><display-name>Penthouse HD 1</display-name><icon src="https://i.imgur.com/nOwGOL8.png"/><url>https://tv.nu</url></channel>
<channel id="PenthouseHD2.us@SD"><display-name>Penthouse HD 2</display-name><icon src="https://i.imgur.com/laGTKSg.png"/><url>https://tv.nu</url></channel>
<channel id="PinkPlus.rs@SD"><display-name>Pink Plus</display-name><icon src="https://i.imgur.com/A3D1RZP.png"/><url>https://tv.nu</url></channel>
<channel id="PlayboyTVEurope.us@SD"><display-name>Playboy TV Europe</display-name><icon src="https://i.imgur.com/5di4Nis.png"/><url>https://tv.nu</url></channel>
<channel id="ProSieben.de@SD"><display-name>ProSieben</display-name><icon src="https://i.imgur.com/zZOk3nh.png"/><url>https://tv.nu</url></channel>
<channel id="Rai1.it@SD"><display-name>Rai 1</display-name><icon src="https://upload.wikimedia.org/wikipedia/commons/thumb/f/fa/Rai_1_-_Logo_2016.svg/960px-Rai_1_-_Logo_2016.svg.png"/><url>https://tv.nu</url></channel>
<channel id="Rai2.it@SD"><display-name>Rai 2</display-name><icon src="https://upload.wikimedia.org/wikipedia/commons/thumb/9/99/Rai_2_-_Logo_2016.svg/960px-Rai_2_-_Logo_2016.svg.png"/><url>https://tv.nu</url></channel>
<channel id="RTL.de@SD"><display-name>RTL</display-name><icon src="https://i.imgur.com/94K94k2.png"/><url>https://tv.nu</url></channel>
<channel id="RTLZwei.de@SD"><display-name>RTLZWEI</display-name><icon src="https://upload.wikimedia.org/wikipedia/commons/thumb/f/f1/RTLZWEI_Logo_2019.svg/960px-RTLZWEI_Logo_2019.svg.png"/><url>https://tv.nu</url></channel>
<channel id="Sjuan.se@SD"><display-name>Sjuan</display-name><icon src="https://upload.wikimedia.org/wikipedia/commons/thumb/1/1f/Sjuan_2018.svg/960px-Sjuan_2018.svg.png"/><url>https://tv.nu</url></channel>
<channel id="SkyNewsInternational.uk@SD"><display-name>Sky News</display-name><icon src="https://upload.wikimedia.org/wikipedia/en/5/57/Sky_News_logo.svg"/><url>https://tv.nu</url></channel>
<channel id="SkyShowtime1.se@SD"><display-name>SkyShowtime 1</display-name><icon src="https://i.imgur.com/Dw9Yv9P.png"/><url>https://tv.nu</url></channel>
<channel id="SkyShowtime2.se@SD"><display-name>SkyShowtime 2</display-name><icon src="https://i.imgur.com/mgiHnYW.png"/><url>https://tv.nu</url></channel>
<channel id="StingrayClassica.ca@SD"><display-name>Stingray Classica</display-name><icon src="https://i.imgur.com/nh1k5RC.png"/><url>https://tv.nu</url></channel>
<channel id="RTLSuper.de@SD"><display-name>Super RTL</display-name><icon src="https://i.imgur.com/KbdK8t9.png"/><url>https://tv.nu</url></channel>
<channel id="SVT1.se@SD"><display-name>SVT1</display-name><icon src="https://i.imgur.com/j6KusQX.png"/><url>https://tv.nu</url></channel>
<channel id="SVT2.se@SD"><display-name>SVT2</display-name><icon src="https://i.imgur.com/pGWvCxp.png"/><url>https://tv.nu</url></channel>
<channel id="SVT24.se@SD"><display-name>SVT24</display-name><icon src="https://i.imgur.com/Ms6qYIV.png"/><url>https://tv.nu</url></channel>
<channel id="SVTBarn.se@SD"><display-name>SVT Barn</display-name><icon src="https://i.imgur.com/ibA8mzG.png"/><url>https://tv.nu</url></channel>
<channel id="TLC.se@SD"><display-name>TLC</display-name><icon src="https://upload.wikimedia.org/wikipedia/commons/thumb/7/74/TLC_Logo.svg/960px-TLC_Logo.svg.png"/><url>https://tv.nu</url></channel>
<channel id="TraceUrban.fr@SD"><display-name>Trace Urban HD</display-name><icon src="https://i.imgur.com/DLIbUMx.png"/><url>https://tv.nu</url></channel>
<channel id="TravelChannelEMEA.uk@SD"><display-name>Travel Channel</display-name><url>https://tv.nu</url></channel>
<channel id="TV2.dk@SD"><display-name>TV2</display-name><icon src="https://i.imgur.com/IZTe8ms.png"/><url>https://tv.nu</url></channel>
<channel id="TV2Direkte.no@SD"><display-name>TV2 (Norge)</display-name><icon src="https://upload.wikimedia.org/wikipedia/commons/thumb/5/53/TV_2_Direkte_%282022-%29.svg/960px-TV_2_Direkte_%282022-%29.svg.png"/><url>https://tv.nu</url></channel>
<channel id="TV3.se@SD"><display-name>TV3</display-name><icon src="https://i.imgur.com/oysCIiw.png"/><url>https://tv.nu</url></channel>
<channel id="TV3Plus.no@SD"><display-name>TV3+</display-name><icon src="https://i.imgur.com/QJdfJKx.png"/><url>https://tv.nu</url></channel>
<channel id="TV3.dk@SD"><display-name>TV3 Danmark</display-name><icon src="https://i.imgur.com/sCr0h4N.png"/><url>https://tv.nu</url></channel>
<channel id="TV3.no@SD"><display-name>TV3 Norge</display-name><icon src="https://i.imgur.com/SAQHN12.png"/><url>https://tv.nu</url></channel>
<channel id="TV4.se@SD"><display-name>TV4</display-name><icon src="https://upload.wikimedia.org/wikipedia/commons/thumb/c/cf/TV4sweden_logo.svg/960px-TV4sweden_logo.svg.png"/><url>https://tv.nu</url></channel>
<channel id="TV4Fakta.se@SD"><display-name>TV4 Fakta</display-name><icon src="https://upload.wikimedia.org/wikipedia/commons/e/ef/TV4_Fakta_Logo_2023.svg"/><url>https://tv.nu</url></channel>
<channel id="TV4Film.se@SD"><display-name>TV4 Film</display-name><icon src="https://upload.wikimedia.org/wikipedia/commons/a/ac/TV4_Film_Logo_2023.svg"/><url>https://tv.nu</url></channel>
<channel id="TV4Fotboll.se@SD"><display-name>TV4 Fotboll</display-name><icon src="https://i.imgur.com/k83j0Nl.png"/><url>https://tv.nu</url></channel>
<channel id="TV4Guld.se@SD"><display-name>TV4 Guld</display-name><icon src="https://upload.wikimedia.org/wikipedia/commons/c/c1/TV4_Guld_Logo_2023.svg"/><url>https://tv.nu</url></channel>
<channel id="TV4Hits.se@SD"><display-name>TV4 Hits</display-name><icon src="https://i.imgur.com/EPYOSwZ.png"/><url>https://tv.nu</url></channel>
<channel id="TV4Hockey.se@SD"><display-name>TV4 Hockey</display-name><icon src="https://i.imgur.com/GZ0rLfa.png"/><url>https://tv.nu</url></channel>
<channel id="TV4Motor.se@SD"><display-name>TV4 Motor</display-name><icon src="https://i.imgur.com/IWEOuwZ.png"/><url>https://tv.nu</url></channel>
<channel id="TV4SportLive1.se@SD"><display-name>TV4 Sport Live 1</display-name><icon src="https://i.imgur.com/rveZPpn.png"/><url>https://tv.nu</url></channel>
<channel id="TV4SportLive2.se@SD"><display-name>TV4 Sport Live 2</display-name><icon src="https://i.imgur.com/a59DoEM.png"/><url>https://tv.nu</url></channel>
<channel id="TV4SportLive3.se@SD"><display-name>TV4 Sport Live 3</display-name><icon src="https://i.imgur.com/zkPpXQB.png"/><url>https://tv.nu</url></channel>
<channel id="TV4SportLive4.se@SD"><display-name>TV4 Sport Live 4</display-name><icon src="https://i.imgur.com/KBHOg6D.png"/><url>https://tv.nu</url></channel>
<channel id="TV4Sportkanalen.se@SD"><display-name>TV4 Sportkanalen</display-name><icon src="https://upload.wikimedia.org/wikipedia/commons/thumb/f/fd/TV4_Sportkanalen_Logo_2023.svg/960px-TV4_Sportkanalen_Logo_2023.svg.png"/><url>https://tv.nu</url></channel>
<channel id="TV4Stars.se@SD"><display-name>TV4 Stars</display-name><icon src="https://i.imgur.com/Sn7QnZa.png"/><url>https://tv.nu</url></channel>
<channel id="TV4Tennis.se@SD"><display-name>TV4 Tennis</display-name><icon src="https://i.imgur.com/ZW4rCG1.png"/><url>https://tv.nu</url></channel>
<channel id="tv5-hd"><display-name>TV5 HD</display-name><url>https://tv.nu</url></channel>
<channel id="TV5MondeEurope.fr@SD"><display-name>TV5 Monde Europe</display-name><icon src="https://i.imgur.com/rPAbMSu.png"/><url>https://tv.nu</url></channel>
<channel id="TV6.se@SD"><display-name>TV6</display-name><icon src="https://i.imgur.com/a9mMd2Q.png"/><url>https://tv.nu</url></channel>
<channel id="TV8.se@SD"><display-name>TV8</display-name><icon src="https://i.imgur.com/OiUyVUx.png"/><url>https://tv.nu</url></channel>
<channel id="TV10.se@SD"><display-name>TV10</display-name><icon src="https://i.imgur.com/unjaCJ6.png"/><url>https://tv.nu</url></channel>
<channel id="TV12.se@SD"><display-name>TV12</display-name><icon src="https://i.imgur.com/ocrwbth.png"/><url>https://tv.nu</url></channel>
<channel id="TVChile.cl@SD"><display-name>TV Chile</display-name><icon src="https://i.imgur.com/oYFto0V.png"/><url>https://tv.nu</url></channel>
<channel id="TVFinland.fi@SD"><display-name>TV Finland</display-name><icon src="https://i.imgur.com/KXWjONv.png"/><url>https://tv.nu</url></channel>
<channel id="TVNorge.no@HD"><display-name>TV Norge HD</display-name><icon src="https://upload.wikimedia.org/wikipedia/commons/thumb/8/8a/TVNorge_Logo_2024.svg/960px-TVNorge_Logo_2024.svg.png"/><url>https://tv.nu</url></channel>
<channel id="TVEInternacionalEuropeAsia.es@SD"><display-name>TVE Internacional</display-name><url>https://tv.nu</url></channel>
<channel id="TVPPolonia.pl@SD"><display-name>TVP Polonia</display-name><icon src="https://upload.wikimedia.org/wikipedia/commons/thumb/1/1a/TVP_Polonia_Logo_2020.svg/960px-TVP_Polonia_Logo_2020.svg.png"/><url>https://tv.nu</url></channel>
<channel id="VFilmAction.se@SD"><display-name>V Film Action</display-name><icon src="https://i.imgur.com/So0mOF8.png"/><url>https://tv.nu</url></channel>
<channel id="VFilmFamily.se@SD"><display-name>V Film Family</display-name><icon src="https://i.imgur.com/K6fQ8pe.png"/><url>https://tv.nu</url></channel>
<channel id="VFilmHits.se@SD"><display-name>V Film Hits</display-name><icon src="https://i.imgur.com/ga6EOsb.png"/><url>https://tv.nu</url></channel>
<channel id="VFilmPremiere.se@SD"><display-name>V Film Premiere</display-name><icon src="https://i.imgur.com/QdFKe21.png"/><url>https://tv.nu</url></channel>
<channel id="VSeries.se@SD"><display-name>V Series</display-name><icon src="https://i.imgur.com/IXWuXB0.png"/><url>https://tv.nu</url></channel>
<channel id="VSport1.se@Sweden"><display-name>V Sport 1</display-name><icon src="https://i.imgur.com/ERWOdjs.png"/><url>https://tv.nu</url></channel>
<channel id="VSportExtra.se@SD"><display-name>V Sport Extra</display-name><icon src="https://i.imgur.com/xwdHxtk.png"/><url>https://tv.nu</url></channel>
<channel id="VSportFootball.se@SD"><display-name>V Sport Football</display-name><icon src="https://i.imgur.com/8zupSOw.png"/><url>https://tv.nu</url></channel>
<channel id="v-sport-football-live-1"><display-name>V Sport Football Live 1</display-name><url>https://tv.nu</url></channel>
<channel id="v-sport-football-live-2"><display-name>V Sport Football Live 2</display-name><url>https://tv.nu</url></channel>
<channel id="v-sport-football-live-3"><display-name>V Sport Football Live 3</display-name><url>https://tv.nu</url></channel>
<channel id="VSportGolf.se@SD"><display-name>V Sport Golf</display-name><icon src="https://i.imgur.com/wCw8Pmz.png"/><url>https://tv.nu</url></channel>
<channel id="VSportLive1.se@SD"><display-name>V Sport Live 1</display-name><icon src="https://i.imgur.com/KGm37xW.png"/><url>https://tv.nu</url></channel>
<channel id="VSportLive2.se@SD"><display-name>V Sport Live 2</display-name><icon src="https://i.imgur.com/mrYUeKy.png"/><url>https://tv.nu</url></channel>
<channel id="VSportLive3.se@SD"><display-name>V Sport Live 3</display-name><icon src="https://i.imgur.com/enr8IAy.png"/><url>https://tv.nu</url></channel>
<channel id="VSportLive4.se@SD"><display-name>V Sport Live 4</display-name><icon src="https://i.imgur.com/yjIXL9k.png"/><url>https://tv.nu</url></channel>
<channel id="VSportLive5.se@SD"><display-name>V Sport Live 5</display-name><icon src="https://i.imgur.com/DToZTJK.png"/><url>https://tv.nu</url></channel>
<channel id="VSportMotor.se@SD"><display-name>V Sport Motor</display-name><icon src="https://i.imgur.com/zspl8AY.png"/><url>https://tv.nu</url></channel>
<channel id="VSportPremium.se@SD"><display-name>V Sport Premium</display-name><icon src="https://i.imgur.com/BGXq2a4.png"/><url>https://tv.nu</url></channel>
<channel id="VSportUltraHD.se@SD"><display-name>V Sport Ultra HD</display-name><icon src="https://i.imgur.com/17OHnMi.png"/><url>https://tv.nu</url></channel>
<channel id="VSportVinter.se@SD"><display-name>V Sport Vinter</display-name><icon src="https://i.imgur.com/1vtjktv.png"/><url>https://tv.nu</url></channel>
<channel id="ViasatExplore.se@SD"><display-name>Viasat Explore</display-name><icon src="https://i.imgur.com/DyT5pKB.png"/><url>https://tv.nu</url></channel>
<channel id="ViasatHistory.se@SD"><display-name>Viasat History</display-name><icon src="https://i.imgur.com/wRP9XA7.png"/><url>https://tv.nu</url></channel>
<channel id="ViasatNature.se@SD"><display-name>Viasat Nature</display-name><icon src="https://i.imgur.com/ousRqqD.png"/><url>https://tv.nu</url></channel>
<channel id="vijuPlusSport.ru@SD"><display-name>Viasat Sport HD</display-name><icon src="https://i.imgur.com/fXESG0l.png"/><url>https://tv.nu</url></channel>
<channel id="TVVisionSverige.se@SD"><display-name>Vision Sverige</display-name><icon src="https://i.imgur.com/nYtwG8h.png"/><url>https://tv.nu</url></channel>
<channel id="VOX.de@SD"><display-name>VOX</display-name><icon src="https://i.imgur.com/QPcmfZb.png"/><url>https://tv.nu</url></channel>
<channel id="WildTV.ca@SD"><display-name>WILD TV HD</display-name><icon src="https://upload.wikimedia.org/wikipedia/en/thumb/a/a7/Wild_TV_logo_2020.png/960px-Wild_TV_logo_2020.png"/><url>https://tv.nu</url></channel>
<channel id="YleTeemaFem.fi@SD"><display-name>Yle Teema &amp; Fem</display-name><icon src="https://upload.wikimedia.org/wikipedia/commons/thumb/0/04/Yle_Teema_%26_Fem.svg/960px-Yle_Teema_%26_Fem.svg.png"/><url>https://tv.nu</url></channel>
<channel id="YleTV1.fi@SD"><display-name>Yle TV1</display-name><icon src="https://i.imgur.com/6yXZwUL.png"/><url>https://tv.nu</url></channel>
<channel id="YleTV2.fi@SD"><display-name>Yle TV2</display-name><icon src="https://i.imgur.com/4xkc6PL.png"/><url>https://tv.nu</url></channel>
<channel id="ZDF.de@SD"><display-name>ZDF</display-name><icon src="https://i.imgur.com/rtLb6m9.png"/><url>https://tv.nu</url></channel>
<programme start="20260423102000 +0000" stop="20260423105000 +0000" channel="3sat.de@SD"><title lang="de">Servicezeit</title><desc lang="de">Das Verbraucher- und Ratgebermagazin im WDR-Fernsehen mit Yvonne Willicks und Dieter Könnes. Verbrauchertipps für jeden Tag. Wirklich preiswert? Wirklich praktisch? Wirklich lecker?Ob Gesundheit oder Geld, Wohnen oder Ernährung, Multimedia oder Verkehr: &quot;Servicezeit&quot; beleuchtet Hintergründe, schafft Orientierung und gibt praktische Ratschläge: und zwar unabhängig und neutral.</desc><category lang="de">Konsument</category></programme>
<programme start="20260423105000 +0000" stop="20260423112000 +0000" channel="3sat.de@SD"><title lang="de">Unkraut</title><desc lang="de">Hartnäckig und hintergründig berichtet die Umweltreportage UNKRAUT über die neuesten Entwicklungen aus dem Bereich Umwelt- und Naturschutz in Bayern. UNKRAUT deckt Umweltsünden auf, spürt nach, was die Menschen bewegt und steht mit Rat und Tat zur Seite.</desc><category lang="de">Natur</category></programme>
<programme start="20260423112000 +0000" stop="20260423120500 +0000" channel="3sat.de@SD"><title lang="de">Maritimes Erbe</title><desc lang="de">Die Südküste von Wales ist seit Jahrhunderten mit der Seefahrt verbunden, aber auch geprägt von Kriegen und Industrie. Ein großer Meeresarm, der Bristolkanal, ragt tief ins britische Kernland hinein. Nördlich des Kanals liegt Wales, das lange für die Wirtschaft des britischen Empire eine besondere Bedeutung hatte ...</desc><category lang="de">Natur</category><category lang="de">Resor</category><episode-num system="xmltv_ns">0.0.0/1</episode-num><episode-num system="onscreen">S01E01</episode-num></programme>
<programme start="20260423120500 +0000" stop="20260423125000 +0000" channel="3sat.de@SD"><title lang="de">Maritimes Erbe</title><desc lang="de">Von Wismar bis zur Insel Usedom erstreckt sich eine Landschaft voller Schönheit und reichem maritimem Erbe. Wilde Strände und Steilküsten, die ihr Gesicht jedes Jahr verändern.</desc><category lang="de">Natur</category><category lang="de">Resor</category><episode-num system="xmltv_ns">0.1.0/1</episode-num><episode-num system="onscreen">S01E02</episode-num></programme>
<programme start="20260423125000 +0000" stop="20260423133000 +0000" channel="3sat.de@SD"><title lang="de">Maritimes Erbe</title><desc lang="de">Die Westküste Norwegens ist reich an maritimer Geschichte und Tradition. Das Nordmeer hat das Leben der Menschen schon immer beherrscht. Und sie haben sich das Meer zunutze gemacht. Von diesem jahrhundertealten Wissen ist die Provinz Møre og Romsdal bis heute geprägt ...</desc><category lang="de">Natur</category><category lang="de">Resor</category><episode-num system="xmltv_ns">0.2.0/1</episode-num><episode-num system="onscreen">S01E03</episode-num></programme>
<programme start="20260423133000 +0000" stop="20260423141500 +0000" channel="3sat.de@SD"><title lang="de">Maritimes Erbe</title><desc lang="de">Die Bretagne ganz im Westen Frankreichs ist ein Sehnsuchtsort. Die riesige Halbinsel, die sich weit in den Atlantik dehnt, ist mit 2.700 Kilometer Küstenlinie eine Region voller Gegensätze. Von den Gezeiten profitieren seit tausend Jahren die Salzbauern und -bäuerinnen, die mit uralter Technik feinstes Meersalz gewinnen ...</desc><category lang="de">Natur</category><category lang="de">Resor</category><episode-num system="xmltv_ns">0.3.0/1</episode-num><episode-num system="onscreen">S01E04</episode-num></programme>
<programme start="20260423141500 +0000" stop="20260423150000 +0000" channel="3sat.de@SD"><title lang="de">Maritimes Erbe</title><desc lang="de">Galicien ist die nordwestlichste Region Spaniens. Vom Rest des Landes durch das gebirgige Hinterland getrennt und umgeben vom wilden Atlantik, hat sich hier eine ganz besondere maritime Ursprünglichkeit bewahrt. Im Nordosten lädt der zerklüftete Kathedralenstrand zum Staunen ein, das felsige Kap Estaca de Bares markiert den nördlichsten Punkt Spaniens.</desc><category lang="de">Natur</category><category lang="de">Resor</category><episode-num system="xmltv_ns">0.4.0/1</episode-num><episode-num system="onscreen">S01E05</episode-num></programme>
<programme start="20260423150000 +0000" stop="20260423154500 +0000" channel="3sat.de@SD"><title lang="de">Maritimes Erbe</title><desc lang="de">Die Küste Liguriens an der Italienischen Riviera ist eines der schönsten und abwechslungsreichsten Meeresufer Europas. An der Westküste finden sich hohe Berge und schmale Sandstrände, und die Ostküste besticht durch die einzigartige Schönheit der Cinque Terre.</desc><category lang="de">Natur</category><category lang="de">Resor</category><episode-num system="xmltv_ns">0.5.0/1</episode-num><episode-num system="onscreen">S01E06</episode-num></programme>
<programme start="20260423154500 +0000" stop="20260423163000 +0000" channel="3sat.de@SD"><title lang="de">Traumorte</title><desc lang="de">Ligurien liegt zwischen Gebirge und Küste. Die Region begeistert mit ihrer rauen Schönheit, in der Natur und Mensch in einzigartiger Harmonie zusammenleben.</desc><category lang="de">Dokumentär</category><category lang="de">Resor</category><episode-num system="xmltv_ns">0.45.0/1</episode-num><episode-num system="onscreen">S01E46</episode-num></programme>
<programme start="20260423163000 +0000" stop="20260423170000 +0000" channel="3sat.de@SD"><title lang="de">nano</title><desc lang="de">Die Welt von morgen</desc><category lang="de">Diskussion</category><category lang="de">Vetenskap</category></programme>
<programme start="20260423170000 +0000" stop="20260423171800 +0000" channel="3sat.de@SD"><title lang="de">heute</title><desc lang="de">20 Minuten für die Nachrichten des Tages. Der relevante Überblick aus der Nachrichtenredaktion des Zweiten Deutschen Fernsehens mit Vertiefung und Einordnung zu den wichtigsten Ereignissen in Deutschland und der Welt.</desc><category lang="de">Nyheter</category></programme>
<programme start="20260423171800 +0000" stop="20260423172000 +0000" channel="3sat.de@SD"><title lang="de">3sat-Wetter</title><desc lang="de">Die Sendung &quot;3sat-Wetter&quot; zeigt die aktuelle Wetterlage und berichtet außerdem über die Wettervorhersage für die nächsten Tage aus den drei folgenden 3sat-Ländern - Deutschland, Österreich und der Schweiz.</desc><category lang="de">Väder</category></programme>
<programme start="20260423172000 +0000" stop="20260423180000 +0000" channel="3sat.de@SD"><title lang="de">Kulturzeit</title><desc lang="de">&quot;Kulturzeit&quot; ist das werktägliche Kulturmagazin von 3sat. &quot;Kulturzeit&quot; mischt sich in kulturelle und gesellschaftspolitische Fragen ein. Das Magazin bietet Hintergrundinformationen, Porträts und Gespräche zu aktuellen und brisanten Fragen.</desc><category lang="de">Diskussion</category></programme>
<programme start="20260423180000 +0000" stop="20260423181500 +0000" channel="3sat.de@SD"><title lang="de">Tagesschau</title><desc lang="de">Die &quot;Tagesschau&quot; bietet die wichtigsten Nachrichten des Tages und zusätzliche Informationen in Text, Bild, Audio und Video sowie umfassende Berichte und Hintergründe zu aktuellen Themen und Entwicklungen. Das Flaggschiff unter den deutschen Nachrichtensendungen ist gleichzeitig die &quot;dienstälteste&quot; noch bestehende Sendung im deutschen Fernsehen. In bis zu 20 am Tag produzierten Sendungen wird die Komplexität des Weltgeschehens verständlich erklärt und in komprimierter Form über aktuelle politische, wirtschaftliche, soziale, kulturelle, sportliche und sonstige Ereignisse berichtet.</desc><category lang="de">Nyheter</category></programme>
<programme start="20260423181500 +0000" stop="20260423190000 +0000" channel="3sat.de@SD"><title lang="de">NANO Doku</title><desc lang="de">Anus und Gesäß gelten als Tabuzone. Dabei sind sie ein Wunderwerk der Evolution. Reporter Anthony Morgan bricht das Schweigen um unser Hinterteil.</desc><category lang="de">Dokumentär</category><episode-num system="xmltv_ns">0.10.0/1</episode-num><episode-num system="onscreen">S01E11</episode-num></programme>
<programme start="20260423190000 +0000" stop="20260423200000 +0000" channel="3sat.de@SD"><title lang="de">nano Talk</title><desc lang="de">Es gilt als sehr wahrscheinlich, dass es außerirdisches Leben gibt. Also höchste Zeit, sich damit zu beschäftigen! Denn sobald wir Gewissheit haben, ändert sich alles für uns.</desc><category lang="de">Diskussion</category><episode-num system="xmltv_ns">0.3.0/1</episode-num><episode-num system="onscreen">S01E04</episode-num></programme>
<programme start="20260423200000 +0000" stop="20260423202500 +0000" channel="3sat.de@SD"><title lang="de">ZIB 2</title><desc lang="de">Das tägliche Nachrichtenmagazin des ORF-Fernsehens.Von Montag bis Freitag liefert &quot;ZIB 2&quot; einen Überblick über die Ereignisse des Tages und bietet dabei vor allem vertiefende Hintergrundinformationen.</desc><category lang="de">Nyheter</category></programme>
<programme start="20260423202500 +0000" stop="20260423205500 +0000" channel="3sat.de@SD"><title lang="de">auslandsjournal extra</title><desc lang="de">In einer globalen und vernetzten Welt gehen Entwicklungen im eigenen Land oft auf Prozesse im Ausland zurück. Diese Komplexität will &quot;auslandsjournal extra&quot; aufzeigen. Die Sendung setzt auf alltagsnahe Geschichten aus fremden Ländern, geht in die Tiefe und sucht nach Geschichten hinter der Geschichte.</desc><category lang="de">Diskussion</category><category lang="de">Politik</category></programme>
<programme start="20260423205500 +0000" stop="20260423215000 +0000" channel="3sat.de@SD"><title lang="de">SRF DOK</title><desc lang="de">Weltweit, auch in der Schweiz, erleben psychedelische Substanzen ein Revival. LSD, MDMA und Psilocybin – manchmal auch in Microdosen – sind aus der Partyszene nicht mehr wegzudenken. Aber auch im medizinischen Kontext werden sie immer häufiger gegen Depressionen oder Suchtkrankheiten eingesetzt.</desc><category lang="de">Dokumentär</category><category lang="de">Hälsa</category></programme>
<programme start="20260423215000 +0000" stop="20260423222500 +0000" channel="3sat.de@SD"><title lang="de">WeltWeit</title><desc lang="de">Rund um den Jahreswechsel gibt es zahlreiche Rituale und Glücksbräuche - Wir verschenken Kleeblätter, Rauchfangkehrer oder Glücksschweinchen, deuten die Zukunft beim Wachsgießen und auch die Feuerwerke und Böller der Silvesternacht waren ursprünglich zum Vertreiben der bösen Geister gedacht. Aberglaube in all seinen Ausformungen gibt es in so gut wie jeder Kultur. Doch warum halten Menschen seit Jahrhunderten an Ritualen fest, deuten Zeichen oder folgen magischen Versprechen? Welchen Platz Aberglaube in unserer modernen Welt einnimmt zwischen Kulturgut und Geschäftemacherei haben sich die WeltWeit-Reporter:innen angeschaut. In Island ist der Glaube an Elfen und Trolle fest in der Kultur der Insel verankert. Diese menschenähnlichen Wesen leben angeblich in Felsen und Hügeln und setzen sich zur Wehr, wenn ihr Lebensraum bedroht ist. Lena Hager trifft eine junge Frau, die als Medium mit Elfen kommuniziert und regelmäßig Zeremonien abhält. Während diese Bräuche für viele Isländerinnen und Isländer mittlerweile für den nostalgischen Blick zurück stehen, hat der Tourismus die alten Traditionen für sich entdeckt. Das Angebot reicht von Souvenirs über Elfentouren bis hin zu Tattoos im Runen-Design. In Ägypten verschwimmt die Grenze zwischen Glauben und Aberglauben. Karim El-Gawhary hat die seltene Gelegenheit, einem sogenannten &quot;Zar&quot; beizuwohnen. Hier wird mit speziellen Ritualen und rhythmischen Gesängen Kontakt zu den Dschinn, den Geistern aus der alten arabischen Mythologie, aufgenommen. &quot;Es ist, als ob ich zum Psychotherapeuten gehe, nach der Sitzung fühle ich mich einfach besser&quot;, sagt eine der Teilnehmerinnen im Interview. Im letzten verbliebenen Stadttor Kairos soll der Geist eines islamischen Heiligen wohnen. Bei der Restaurierung sind unzählige Fundstücke zum Vorschein gekommen, die belegen, wie sehr die Menschen an seine Existenz glauben. In Italien ist Neapel die Stadt, in der der Aberglaube zu Hause ist. Nichts geht ohne das Corno oder Cornicello, ein Amulett, das Missgunst und Neid von einem abhalten soll. Die Einheimischen verschenken es bei jeder Gelegenheit, denn in der Stadt gilt das Motto - Es ist zwar nicht wahr, aber ich glaube daran. Und in der Zwischenzeit haben die Menschen auch entdeckt, dass sich mit dem Aberglauben ein gutes Geschäft machen lässt. Cornelia Vospernik taucht ein in die Mysterien der Stadt und erfährt, dass es hier den einzigen Totenschädel mit Ohren gibt, weil er sich so viele Gebete und Fürbitten anhören muss, sagt die Überlieferung.</desc><category lang="de">Dokumentär</category><category lang="de">Mijö</category><category lang="de">Vetenskap</category><episode-num system="xmltv_ns">0.51.0/1</episode-num><episode-num system="onscreen">S01E52</episode-num></programme>
<programme start="20260423222500 +0000" stop="20260423225000 +0000" channel="3sat.de@SD"><title lang="de">10 vor 10</title><desc lang="de">„10vor10“ ist eine News-Magazin vom Schweizer Radio und Fernsehen (SRF). Hintergründe zu den Schlagzeilen des Tages, vertiefende Berichte, Reportagen, Porträts und Live-Gespräche informieren über die wichtigsten Themen aus der Schweiz und der Welt.</desc><category lang="de">Nyheter</category></programme>
<programme start="20260423225000 +0000" stop="20260424000500 +0000" channel="3sat.de@SD"><title lang="de">maischberger</title><desc lang="de">Bärbel Bas, SPD Bundesarbeitsministerin Vassili Golod, ARD Ursula Wagner Tochter fiel im Ukrainekrieg Petra Gerster Moderatorin und Autorin Sven Gösmann, dpa Mariam Lau, Die Zeit</desc><category lang="de">Diskussion</category><category lang="de">Underhållning</category></programme>
<programme start="20260424000500 +0000" stop="20260424003500 +0000" channel="3sat.de@SD"><title lang="de">Die Nordreportage</title><desc lang="de">Der historische Getreidespeicher in Bremen galt vor rund 100 Jahren als einer der modernsten Umschlagsplätze für Getreide. Heute ist der &quot;Koloss von Bremen&quot; ein Industriedenkmal: und dennoch weiterhin Anlaufpunkt für Schiffe aus verschiedenen Ländern. &quot;Die Nordreportage&quot; begleitet die Menschen vom alten Getreidespeicher, ist dabei, wenn sich Arbeiter an 20 Meter hohen Betonwänden abseilen, um Silozellen für Frischware vorzubereiten.</desc><category lang="de">Dokumentär</category></programme>
<programme start="20260424003500 +0000" stop="20260424012000 +0000" channel="3sat.de@SD"><title lang="de">Maritimes Erbe</title><desc lang="de">Die Südküste von Wales ist seit Jahrhunderten mit der Seefahrt verbunden, aber auch geprägt von Kriegen und Industrie. Ein großer Meeresarm, der Bristolkanal, ragt tief ins britische Kernland hinein. Nördlich des Kanals liegt Wales, das lange für die Wirtschaft des britischen Empire eine besondere Bedeutung hatte ...</desc><category lang="de">Natur</category><category lang="de">Resor</category><episode-num system="xmltv_ns">0.0.0/1</episode-num><episode-num system="onscreen">S01E01</episode-num></programme>
<programme start="20260424012000 +0000" stop="20260424020500 +0000" channel="3sat.de@SD"><title lang="de">Maritimes Erbe</title><desc lang="de">Von Wismar bis zur Insel Usedom erstreckt sich eine Landschaft voller Schönheit und reichem maritimem Erbe. Wilde Strände und Steilküsten, die ihr Gesicht jedes Jahr verändern.</desc><category lang="de">Natur</category><category lang="de">Resor</category><episode-num system="xmltv_ns">0.1.0/1</episode-num><episode-num system="onscreen">S01E02</episode-num></programme>
<programme start="20260424020500 +0000" stop="20260424025000 +0000" channel="3sat.de@SD"><title lang="de">Maritimes Erbe</title><desc lang="de">Die Westküste Norwegens ist reich an maritimer Geschichte und Tradition. Das Nordmeer hat das Leben der Menschen schon immer beherrscht. Und sie haben sich das Meer zunutze gemacht. Von diesem jahrhundertealten Wissen ist die Provinz Møre og Romsdal bis heute geprägt ...</desc><category lang="de">Natur</category><category lang="de">Resor</category><episode-num system="xmltv_ns">0.2.0/1</episode-num><episode-num system="onscreen">S01E03</episode-num></programme>
<programme start="20260424025000 +0000" stop="20260424033500 +0000" channel="3sat.de@SD"><title lang="de">Maritimes Erbe</title><desc lang="de">Die Bretagne ganz im Westen Frankreichs ist ein Sehnsuchtsort. Die riesige Halbinsel, die sich weit in den Atlantik dehnt, ist mit 2.700 Kilometer Küstenlinie eine Region voller Gegensätze. Von den Gezeiten profitieren seit tausend Jahren die Salzbauern und -bäuerinnen, die mit uralter Technik feinstes Meersalz gewinnen ...</desc><category lang="de">Natur</category><category lang="de">Resor</category><episode-num system="xmltv_ns">0.3.0/1</episode-num><episode-num system="onscreen">S01E04</episode-num></programme>
<programme start="20260424033500 +0000" stop="20260424042000 +0000" channel="3sat.de@SD"><title lang="de">Maritimes Erbe</title><desc lang="de">Galicien ist die nordwestlichste Region Spaniens. Vom Rest des Landes durch das gebirgige Hinterland getrennt und umgeben vom wilden Atlantik, hat sich hier eine ganz besondere maritime Ursprünglichkeit bewahrt. Im Nordosten lädt der zerklüftete Kathedralenstrand zum Staunen ein, das felsige Kap Estaca de Bares markiert den nördlichsten Punkt Spaniens.</desc><category lang="de">Natur</category><category lang="de">Resor</category><episode-num system="xmltv_ns">0.4.0/1</episode-num><episode-num system="onscreen">S01E05</episode-num></programme>
<programme start="20260423100000 +0000" stop="20260423110000 +0000" channel="TV3Plus.dk@SD"><title lang="sv">Hawaii Five-0</title><desc lang="sv">Kriminalbetjent Steve McGarrett vender hjem til Oahu for at efterforske sin fars mord og bliver overtalt af guvernøren til at blive og lede en ny specialstyrke.</desc><category lang="sv">Action</category><category lang="sv">Drama</category><category lang="sv">Kriminalare</category><episode-num system="xmltv_ns">7.10.0/1</episode-num><episode-num system="onscreen">S08E11</episode-num></programme>
<programme start="20260423110000 +0000" stop="20260423120000 +0000" channel="TV3Plus.dk@SD"><title lang="sv">Hawaii Five-0</title><desc lang="sv">Kriminalbetjent Steve McGarrett vender hjem til Oahu for at efterforske sin fars mord og bliver overtalt af guvernøren til at blive og lede en ny specialstyrke.</desc><category lang="sv">Action</category><category lang="sv">Drama</category><category lang="sv">Kriminalare</category><episode-num system="xmltv_ns">7.11.0/1</episode-num><episode-num system="onscreen">S08E12</episode-num></programme>
<programme start="20260423120000 +0000" stop="20260423130000 +0000" channel="TV3Plus.dk@SD"><title lang="sv">Forsvundet sporløst</title><desc lang="sv">Holdet leder efter en såret amerikansk soldat Kevin Grant, som for nylig er vendt hjem fra krigen. Grant opdagede, at hans forretning var gået konkurs, og han er ved at miste sit og hans forlovedes hjem.</desc><category lang="sv">Drama</category><category lang="sv">Kriminalare</category><category lang="sv">Mysterium</category><episode-num system="xmltv_ns">1.16.0/1</episode-num><episode-num system="onscreen">S02E17</episode-num></programme>
<programme start="20260423130000 +0000" stop="20260423140500 +0000" channel="TV3Plus.dk@SD"><title lang="sv">Forsvundet sporløst</title><desc lang="sv">George skændes med sin kone i hendes frisørsalon, går ud for at indbetale dagens indtjening og vender aldrig tilbage. Da holdet finder tegn på et slagsmål i salonen, mistænker de Georges kone og deres arbejdsløse søn.</desc><category lang="sv">Drama</category><category lang="sv">Kriminalare</category><category lang="sv">Mysterium</category><episode-num system="xmltv_ns">1.17.0/1</episode-num><episode-num system="onscreen">S02E18</episode-num></programme>
<programme start="20260423140500 +0000" stop="20260423150000 +0000" channel="TV3Plus.dk@SD"><title lang="sv">NCIS - Los Angeles</title><desc lang="sv">Inden for den amerikanske marines efterforskningsorgan, NCIS, findes en specialafdeling, hvor man tager sig af de allerfarligste forbrydere, som udgør en trussel for landets sikkerhed.</desc><category lang="sv">Action</category><category lang="sv">Drama</category><category lang="sv">Kriminalare</category><episode-num system="xmltv_ns">7.1.0/1</episode-num><episode-num system="onscreen">S08E02</episode-num></programme>
<programme start="20260423150000 +0000" stop="20260423160000 +0000" channel="TV3Plus.dk@SD"><title lang="sv">Superliga Studiet</title><desc lang="sv">Se med, når vi varmer op til den forestående 3F Superliga-kamp mellem FC Nordsjælland og AGF.</desc><category lang="sv">Fotboll</category><category lang="sv">Sportsnack</category></programme>
<programme start="20260423160000 +0000" stop="20260423180000 +0000" channel="TV3Plus.dk@SD"><title lang="sv">3F Superliga</title><desc lang="sv">I 3F Superligaens mesterskabsspil tager man fat på 2. halvdel, når FC Nordsjælland får besøg af AGF i 6. spillerunde. Værterne har haft et forrygende forår med bl.a. 13 af 15 mulige point i mesterskabsspillet, så de har fået et lille forspring på 3.-pladsen, hvor de nu er favoritter i den tætte kamp om bronzemedaljerne. Gæsterne har haft en fornem sæson, hvor aarhusianerne jagter deres 1. mesterskab siden 1985/86, men de er gået en smule i stå på det seneste, og FC Midtjylland er lige i hælene på dem. Hjemme henter FC Nordsjælland de fleste af deres point, men det tegner tæt mod AGF, der er ligaens bedste udehold.</desc><category lang="sv">Fotboll</category><category lang="sv">Sport</category></programme>
<programme start="20260423180000 +0000" stop="20260423201500 +0000" channel="TV3Plus.dk@SD"><title lang="sv">Onside</title><desc lang="sv">Signe Vadgaard og vores fodboldeksperter guider dig igennem alle ugens højdepunkter i Superligaen. Du får fyldige sammendrag, spændende reportager og reaktioner fra rundens kampe i Onside.</desc><category lang="sv">Fotboll</category><category lang="sv">Sport</category><category lang="sv">Sportsnack</category></programme>
<programme start="20260423201500 +0000" stop="20260423224500 +0000" channel="TV3Plus.dk@SD"><title lang="sv">God Is a Bullet</title><desc lang="sv">Da kriminalbetjent Bob Hightower finder sin ekskone myrdet og sin datter kidnappet af en sadistisk sekt, tager han sagen i egne hænder. Med hjælp fra Case Hardin, en kvinde som tidligere er lykkedes med at flygte fra sekten, infiltrerer han den hemmelige sekt. Nu må han forsøge at redde sin datter og samtidig få hævn over mordet på sin eks og de grusomheder Case er blevet udsat for af sektenes gale leder.</desc><category lang="sv">Action</category><category lang="sv">Kriminalare</category><category lang="sv">Thriller</category></programme>
<programme start="20260423224500 +0000" stop="20260424004500 +0000" channel="TV3Plus.dk@SD"><title lang="sv">Monster Hunter</title><desc lang="sv">Efter en gruppe soldater rammes af en uventet sandstorm, transporteres de til en verden som findes bag vores egen - en verden, hvor mægtige monstre hersker med dødbringende brutalitet.</desc><category lang="sv">Action</category><category lang="sv">Fantasy</category><category lang="sv">Science fiction</category></programme>
<programme start="20260424004500 +0000" stop="20260424014000 +0000" channel="TV3Plus.dk@SD"><title lang="sv">NCIS</title><desc lang="sv">I dette populære politidrama følger vi den amerikanske flådes efterforskere fra afdelingen NCIS med specialagent Gibbs i front. Gibbs og hans team løser alle sager fra mord og mishandling til terrorisme og spionage.</desc><category lang="sv">Action</category><category lang="sv">Drama</category><category lang="sv">Kriminalare</category><episode-num system="xmltv_ns">21.17.0/1</episode-num><episode-num system="onscreen">S22E18</episode-num></programme>
<programme start="20260424014000 +0000" stop="20260424025000 +0000" channel="TV3Plus.dk@SD"><title lang="sv">The Head</title><desc lang="sv">Der er uvejr på vej, så holdets søgen efter Annika må afbrydes. Johan prøver at presse Maggie til at huske, hvad der skete efter Miles&apos; død. Derudover begraver Nils en blodig sav i isen...</desc><category lang="sv">Mysterium</category><category lang="sv">Thriller</category><episode-num system="xmltv_ns">0.1.0/1</episode-num><episode-num system="onscreen">S01E02</episode-num></programme>
<programme start="20260424025000 +0000" stop="20260424040000 +0000" channel="TV3Plus.dk@SD"><title lang="sv">The Head</title><desc lang="sv">Maggie prøver stadig at huske, hvad der er sket, men Arthur advarer Johan mod at stole på hende. Morderen må være en af vinter-efterforskerne. Men hvem? Hvorfor? Og kan de overlevende flygte?</desc><category lang="sv">Mysterium</category><category lang="sv">Thriller</category><episode-num system="xmltv_ns">0.2.0/1</episode-num><episode-num system="onscreen">S01E03</episode-num></programme>
<programme start="20260424040000 +0000" stop="20260424043000 +0000" channel="TV3Plus.dk@SD"><title lang="sv">Men at Work</title><desc lang="sv">Gibbs går med til at gifte sig med sin britiske kæreste, så hun kan få opholdstilladelse. Samtidig bliver Milo oprevet over at finde ud af, at hans nye kæreste er gode venner og forretningspartner med sin kvindelige eks.</desc><category lang="sv">Drama</category><category lang="sv">Komedi</category><episode-num system="xmltv_ns">2.3.0/1</episode-num><episode-num system="onscreen">S03E04</episode-num></programme>
<programme start="20260424043000 +0000" stop="20260424052000 +0000" channel="TV3Plus.dk@SD"><title lang="sv">Pacific Blue</title><desc lang="sv">En snedig bandit på mountainbike røver fra folk, der sidder fast i trafikpropper, ved at true dem med sin pistol og efterfølgende flygte gennem smalle gader nær stranden.</desc><category lang="sv">Action</category><category lang="sv">Drama</category><category lang="sv">Kriminalare</category><episode-num system="xmltv_ns">0.12.0/1</episode-num><episode-num system="onscreen">S01E13</episode-num></programme>
<programme start="20260424052000 +0000" stop="20260424061500 +0000" channel="TV3Plus.dk@SD"><title lang="sv">Pacific Blue</title><desc lang="sv">En teknikfjendtlig terrorist placerer bomber rundt omkring på stranden og vil kun lade T.C. og Victor demontere dem. Han vil have al strøm i Santa Monica lukket ned i tolv timer første dag i måneden.</desc><category lang="sv">Action</category><category lang="sv">Drama</category><category lang="sv">Kriminalare</category><episode-num system="xmltv_ns">1.0.0/1</episode-num><episode-num system="onscreen">S02E01</episode-num></programme>
<programme start="20260424061500 +0000" stop="20260424070500 +0000" channel="TV3Plus.dk@SD"><title lang="sv">Forsvundet sporløst</title><desc lang="sv">Holdet leder efter en såret amerikansk soldat Kevin Grant, som for nylig er vendt hjem fra krigen. Grant opdagede, at hans forretning var gået konkurs, og han er ved at miste sit og hans forlovedes hjem.</desc><category lang="sv">Drama</category><category lang="sv">Kriminalare</category><category lang="sv">Mysterium</category><episode-num system="xmltv_ns">1.16.0/1</episode-num><episode-num system="onscreen">S02E17</episode-num></programme>
<programme start="20260424070500 +0000" stop="20260424075500 +0000" channel="TV3Plus.dk@SD"><title lang="sv">Forsvundet sporløst</title><desc lang="sv">George skændes med sin kone i hendes frisørsalon, går ud for at indbetale dagens indtjening og vender aldrig tilbage. Da holdet finder tegn på et slagsmål i salonen, mistænker de Georges kone og deres arbejdsløse søn.</desc><category lang="sv">Drama</category><category lang="sv">Kriminalare</category><category lang="sv">Mysterium</category><episode-num system="xmltv_ns">1.17.0/1</episode-num><episode-num system="onscreen">S02E18</episode-num></programme>
<programme start="20260424075500 +0000" stop="20260424090000 +0000" channel="TV3Plus.dk@SD"><title lang="sv">S.W.A.T.</title><desc lang="sv">En ung, sort mand bliver ved en fejl skudt af lederen for S.W.A.T. og Daniel Hondo Harrelsson, som er født og opvokset i området, tvinges til at tage rollen som ny leder.</desc><category lang="sv">Action</category><category lang="sv">Drama</category><category lang="sv">Kriminalare</category></programme>
<programme start="20260424090000 +0000" stop="20260424100000 +0000" channel="TV3Plus.dk@SD"><title lang="sv">S.W.A.T.</title><desc lang="sv">Hondo og Deacon skal bruge alt deres SWAT træning og færdigheder for at undvige en flok væbnede lejesoldater, der jagter dem i Angeles Mountains efter et baghold.</desc><category lang="sv">Action</category><category lang="sv">Drama</category><category lang="sv">Kriminalare</category><episode-num system="xmltv_ns">0.20.0/1</episode-num><episode-num system="onscreen">S01E21</episode-num></programme>
<programme start="20260424100000 +0000" stop="20260424110500 +0000" channel="TV3Plus.dk@SD"><title lang="sv">Hawaii Five-0</title><desc lang="sv">Kriminalbetjent Steve McGarrett vender hjem til Oahu for at efterforske sin fars mord og bliver overtalt af guvernøren til at blive og lede en ny specialstyrke.</desc><category lang="sv">Action</category><category lang="sv">Drama</category><category lang="sv">Kriminalare</category><episode-num system="xmltv_ns">7.11.0/1</episode-num><episode-num system="onscreen">S08E12</episode-num></programme>
<programme start="20260424110500 +0000" stop="20260424120500 +0000" channel="TV3Plus.dk@SD"><title lang="sv">Hawaii Five-0</title><desc lang="sv">Krimiserie. Da en mand, der er sigtet for at have dræbt sin kone, truer med at begå selvmord, afslører Grover at også han engang var tæt på at tage sit eget liv.</desc><category lang="sv">Action</category><category lang="sv">Drama</category><category lang="sv">Kriminalare</category><episode-num system="xmltv_ns">7.12.0/1</episode-num><episode-num system="onscreen">S08E13</episode-num></programme>
<programme start="20260424120500 +0000" stop="20260424130500 +0000" channel="TV3Plus.dk@SD"><title lang="sv">Forsvundet sporløst</title><desc lang="sv">Mens de leder efter Julie Cochran, en kvinde fra Manhattan, der forsvandt den morgen, hun skulle have forladt byen, mistænker holdet hendes kæreste Greg Knowles.</desc><category lang="sv">Drama</category><category lang="sv">Kriminalare</category><category lang="sv">Mysterium</category><episode-num system="xmltv_ns">1.18.0/1</episode-num><episode-num system="onscreen">S02E19</episode-num></programme>
<programme start="20260424130500 +0000" stop="20260424140500 +0000" channel="TV3Plus.dk@SD"><title lang="sv">Forsvundet sporløst</title><desc lang="sv">Da Martins tante Bonnie, en svag kræftpatient og sygeplejerske, forsvinder i flere timer, beder hendes bekymrede mand og voksne døtre Martin om hjælp med at finde hende.</desc><category lang="sv">Drama</category><category lang="sv">Kriminalare</category><category lang="sv">Mysterium</category><episode-num system="xmltv_ns">1.19.0/1</episode-num><episode-num system="onscreen">S02E20</episode-num></programme>
<programme start="20260424140500 +0000" stop="20260424151000 +0000" channel="TV3Plus.dk@SD"><title lang="sv">NCIS - Los Angeles</title><desc lang="sv">NCIS LA holdet efterforsker en bortførelsessag, mens de mangler to på holdet, med Hetty i D.C til afhøring og en anden stadig i ICU efter missionen i Syrien.</desc><category lang="sv">Action</category><category lang="sv">Drama</category><category lang="sv">Kriminalare</category><episode-num system="xmltv_ns">7.2.0/1</episode-num><episode-num system="onscreen">S08E03</episode-num></programme>
<programme start="20260424151000 +0000" stop="20260424161000 +0000" channel="TV3Plus.dk@SD"><title lang="sv">NCIS - Los Angeles</title><desc lang="sv">Efter en agent fra Homeland Security er blevet forgiftet af en Triad-lejemorder, finder NCIS et varelager med falske mærkevarer og et spor, der fører til stjålne statslige penge.</desc><category lang="sv">Action</category><category lang="sv">Drama</category><category lang="sv">Kriminalare</category><episode-num system="xmltv_ns">7.3.0/1</episode-num><episode-num system="onscreen">S08E04</episode-num></programme>
<programme start="20260424161000 +0000" stop="20260424170500 +0000" channel="TV3Plus.dk@SD"><title lang="sv">NCIS</title><desc lang="sv">I dette populære politidrama følger vi den amerikanske flådes efterforskere fra afdelingen NCIS med specialagent Gibbs i front. Gibbs og hans team løser alle sager fra mord og mishandling til terrorisme og spionage.</desc><category lang="sv">Action</category><category lang="sv">Drama</category><category lang="sv">Kriminalare</category><episode-num system="xmltv_ns">21.18.0/1</episode-num><episode-num system="onscreen">S22E19</episode-num></programme>
<programme start="20260424170500 +0000" stop="20260424180000 +0000" channel="TV3Plus.dk@SD"><title lang="sv">NCIS</title><desc lang="sv">I dette populære politidrama følger vi den amerikanske flådes efterforskere fra afdelingen NCIS med specialagent Gibbs i front. Gibbs og hans team løser alle sager fra mord og mishandling til terrorisme og spionage.</desc><category lang="sv">Action</category><category lang="sv">Drama</category><category lang="sv">Kriminalare</category><episode-num system="xmltv_ns">21.19.0/1</episode-num><episode-num system="onscreen">S22E20</episode-num></programme>
<programme start="20260424180000 +0000" stop="20260424190000 +0000" channel="TV3Plus.dk@SD"><title lang="sv">NCIS - Hawai&apos;i</title><desc lang="sv">Den første kvindelige leder af NCIS Pearl Harbor, Jane Tennant, er steget op gennem graderne i et system, der har modarbejdet hende hvert eneste skridt på vejen.</desc><category lang="sv">Action</category><category lang="sv">Drama</category><category lang="sv">Kriminalare</category><episode-num system="xmltv_ns">0.20.0/1</episode-num><episode-num system="onscreen">S01E21</episode-num></programme>
<programme start="20260424190000 +0000" stop="20260424211500 +0000" channel="TV3Plus.dk@SD"><title lang="sv">xXx 2: The Next Level</title><desc lang="sv">Den modige agent, Augustus Gibbons, der er leder af National Security Agency, bliver sammen med sin makker, teknikeksperten Toby Lee Shavers, udsat for et dødbringende attentat i det tophemmelige operationscenter, og de når med nød og næppe at undslippe.</desc><category lang="sv">Action</category><category lang="sv">Äventyr</category><category lang="sv">Kriminalare</category></programme>
<programme start="20260424211500 +0000" stop="20260425000000 +0000" channel="TV3Plus.dk@SD"><title lang="sv">Creed</title><desc lang="sv">Adonis Johnson, søn af den afdøde verdensmester i sværvægt, Apollo Creed, drømmer om sin egen plads i boksehistorien. Han drager til Philadelphia og overtaler sin fars gamle rival Rocky Balboa, til at træne ham.</desc><category lang="sv">Action</category><category lang="sv">Drama</category></programme>
<programme start="20260425000000 +0000" stop="20260425005000 +0000" channel="TV3Plus.dk@SD"><title lang="sv">NCIS - Hawai&apos;i</title><desc lang="sv">Den første kvindelige leder af NCIS Pearl Harbor, Jane Tennant, er steget op gennem graderne i et system, der har modarbejdet hende hvert eneste skridt på vejen.</desc><category lang="sv">Action</category><category lang="sv">Drama</category><category lang="sv">Kriminalare</category><episode-num system="xmltv_ns">0.20.0/1</episode-num><episode-num system="onscreen">S01E21</episode-num></programme>
<programme start="20260425005000 +0000" stop="20260425015000 +0000" channel="TV3Plus.dk@SD"><title lang="sv">NCIS</title><desc lang="sv">I dette populære politidrama følger vi den amerikanske flådes efterforskere fra afdelingen NCIS med specialagent Gibbs i front. Gibbs og hans team løser alle sager fra mord og mishandling til terrorisme og spionage.</desc><category lang="sv">Action</category><category lang="sv">Drama</category><category lang="sv">Kriminalare</category><episode-num system="xmltv_ns">21.18.0/1</episode-num><episode-num system="onscreen">S22E19</episode-num></programme>
<programme start="20260425015000 +0000" stop="20260425025500 +0000" channel="TV3Plus.dk@SD"><title lang="sv">The Head</title><desc lang="sv">Maggie prøver stadig at huske, hvad der er sket, men Arthur advarer Johan mod at stole på hende. Morderen må være en af vinter-efterforskerne. Men hvem? Hvorfor? Og kan de overlevende flygte?</desc><category lang="sv">Mysterium</category><category lang="sv">Thriller</category><episode-num system="xmltv_ns">0.2.0/1</episode-num><episode-num system="onscreen">S01E03</episode-num></programme>
<programme start="20260425025500 +0000" stop="20260425040000 +0000" channel="TV3Plus.dk@SD"><title lang="sv">The Head</title><desc lang="sv">Arthur afslører, at liget, der blev fundet i sneen, er selveste forskeren Sarah Jackson. Hun døde for flere år siden under Polaris V-ulykken; en mislykket mission, der endte i en tragedie.</desc><category lang="sv">Mysterium</category><category lang="sv">Thriller</category><episode-num system="xmltv_ns">0.3.0/1</episode-num><episode-num system="onscreen">S01E04</episode-num></programme>
</tv>