<?xml version="1.0" encoding="UTF-8" ?><tv date="20260423">
<channel id="AFNSports.us@SD"><display-name>AFN|sports</display-name><icon src="https://i.imgur.com/dGRhc5A.png"/><url>https://v3.myafn.dodmedia.osd.mil</url></channel>
<channel id="AFNPrimeAtlantic.us@SD"><display-name>AFN|prime Atlantic</display-name><icon src="https://i.imgur.com/IcCyQEh.png"/><url>https://v3.myafn.dodmedia.osd.mil</url></channel>
<channel id="AFNSpectrum.us@SD"><display-name>AFN|spectrum</display-name><icon src="https://i.imgur.com/kepHNgX.png"/><url>https://v3.myafn.dodmedia.osd.mil</url></channel>
<channel id="AFNPrimePacific.us@SD"><display-name>AFN|prime Pacific</display-name><icon src="https://i.imgur.com/35ZmoAI.png"/><url>https://v3.myafn.dodmedia.osd.mil</url></channel>
<channel id="AFNNews.us@SD"><display-name>AFN|news</display-name><icon src="https://i.imgur.com/NB5m2OG.png"/><url>https://v3.myafn.dodmedia.osd.mil</url></channel>
<channel id="AFNSports2.us@SD"><display-name>AFN|sports2</display-name><icon src="https://i.imgur.com/AIsjtPz.png"/><url>https://v3.myafn.dodmedia.osd.mil</url></channel>
<channel id="AFNFamily.us@SD"><display-name>AFN|pulse</display-name><icon src="https://i.imgur.com/N0OY1Hg.png"/><url>https://v3.myafn.dodmedia.osd.mil</url></channel>
<channel id="AFNMovie.us@SD"><display-name>AFN|movie</display-name><icon src="https://i.imgur.com/8ajBB5n.png"/><url>https://v3.myafn.dodmedia.osd.mil</url></channel>
</tv>