<?xml version='1.0' encoding='utf-8'?>
<tv date="20260424">
  <channel id="NHKWorldPremium.jp@SD">
    <display-name>NHK World Premium</display-name>
    <icon src="https://i.imgur.com/4ESi2La.png" />
    <url>https://nhkworldpremium.com</url>
  </channel>
  <channel id="NHKWorldPremium.jp@SD">
    <display-name>NHK World Premium</display-name>
    <icon src="https://i.imgur.com/4ESi2La.png" />
    <url>https://nhkworldpremium.com</url>
  </channel>
  <programme start="20260423152900 +0000" stop="20260423153000 +0000" channel="NHKWorldPremium.jp@SD">
    <title lang="en">World Weather</title>
  </programme>
  <programme start="20260423152900 +0000" stop="20260423153000 +0000" channel="NHKWorldPremium.jp@SD">
    <title lang="ja">ワールドウェザー</title>
  </programme>
  <programme start="20260423153000 +0000" stop="20260423160000 +0000" channel="NHKWorldPremium.jp@SD">
    <title lang="en">Familiarization with Japanese Traditional Performing Arts</title>
  </programme>
  <programme start="20260423153000 +0000" stop="20260423160000 +0000" channel="NHKWorldPremium.jp@SD">
    <title lang="ja">芸能きわみ堂</title>
    <sub-title lang="ja">選　檜舞台を彩る！名刀と立廻り</sub-title>
  </programme>
  <programme start="20260423160000 +0000" stop="20260423160500 +0000" channel="NHKWorldPremium.jp@SD">
    <title lang="en">Child-Rearing Hints &amp; Tips mini</title>
  </programme>
  <programme start="20260423160000 +0000" stop="20260423160500 +0000" channel="NHKWorldPremium.jp@SD">
    <title lang="ja">まいにちスクスク</title>
  </programme>
  <programme start="20260423160500 +0000" stop="20260423161000 +0000" channel="NHKWorldPremium.jp@SD">
    <title lang="en">Child-Rearing Hints &amp; Tips mini</title>
  </programme>
  <programme start="20260423160500 +0000" stop="20260423161000 +0000" channel="NHKWorldPremium.jp@SD">
    <title lang="ja">まいにちスクスク</title>
  </programme>
  <programme start="20260423161000 +0000" stop="20260423161500 +0000" channel="NHKWorldPremium.jp@SD">
    <title lang="en">Ukiyoe EDO-LIFE</title>
  </programme>
  <programme start="20260423161000 +0000" stop="20260423161500 +0000" channel="NHKWorldPremium.jp@SD">
    <title lang="ja">浮世絵EDO-LIFE</title>
  </programme>
  <programme start="20260423161500 +0000" stop="20260423164000 +0000" channel="NHKWorldPremium.jp@SD">
    <title lang="en">Today's Cooking</title>
  </programme>
  <programme start="20260423161500 +0000" stop="20260423164000 +0000" channel="NHKWorldPremium.jp@SD">
    <title lang="ja">きょうの料理</title>
    <sub-title lang="ja">「京料理人のモダン和ごはん」和風ポークソテー</sub-title>
  </programme>
  <programme start="20260423164000 +0000" stop="20260423171000 +0000" channel="NHKWorldPremium.jp@SD">
    <title lang="en">Shogi Focus</title>
  </programme>
  <programme start="20260423164000 +0000" stop="20260423171000 +0000" channel="NHKWorldPremium.jp@SD">
    <title lang="ja">将棋フォーカス</title>
  </programme>
  <programme start="20260423171000 +0000" stop="20260423174000 +0000" channel="NHKWorldPremium.jp@SD">
    <title lang="en">asaichi on ETV</title>
  </programme>
  <programme start="20260423171000 +0000" stop="20260423174000 +0000" channel="NHKWorldPremium.jp@SD">
    <title lang="ja">Eテレであさイチ</title>
    <sub-title lang="ja">教えて名店さん！（1）極上ポテトサラダ</sub-title>
  </programme>
  <programme start="20260423174000 +0000" stop="20260423174500 +0000" channel="NHKWorldPremium.jp@SD">
    <title lang="en">World Weather</title>
  </programme>
  <programme start="20260423174000 +0000" stop="20260423174500 +0000" channel="NHKWorldPremium.jp@SD">
    <title lang="ja">ワールドウェザー</title>
  </programme>
  <programme start="20260423174500 +0000" stop="20260423180000 +0000" channel="NHKWorldPremium.jp@SD">
    <title lang="en">Kid's Discovery</title>
  </programme>
  <programme start="20260423174500 +0000" stop="20260423180000 +0000" channel="NHKWorldPremium.jp@SD">
    <title lang="ja">みいつけた！</title>
  </programme>
  <programme start="20260423180000 +0000" stop="20260423182500 +0000" channel="NHKWorldPremium.jp@SD">
    <title lang="en">With Mother</title>
  </programme>
  <programme start="20260423180000 +0000" stop="20260423182500 +0000" channel="NHKWorldPremium.jp@SD">
    <title lang="ja">おかあさんといっしょ</title>
  </programme>
  <programme start="20260423182500 +0000" stop="20260423183000 +0000" channel="NHKWorldPremium.jp@SD">
    <title lang="en">Hello! NHK WORLD-JAPAN</title>
  </programme>
  <programme start="20260423182500 +0000" stop="20260423183000 +0000" channel="NHKWorldPremium.jp@SD">
    <title lang="ja">ハロー！NHKワールドJAPAN</title>
  </programme>
  <programme start="20260423183000 +0000" stop="20260423184500 +0000" channel="NHKWorldPremium.jp@SD">
    <title lang="en">Drama Serial "The Scent of the Wind"</title>
    <sub-title lang="en">Ep. 19</sub-title>
  </programme>
  <programme start="20260423183000 +0000" stop="20260423184500 +0000" channel="NHKWorldPremium.jp@SD">
    <title lang="ja">連続テレビ小説「風、薫る」</title>
    <sub-title lang="ja">（19）</sub-title>
  </programme>
  <programme start="20260423184500 +0000" stop="20260423193000 +0000" channel="NHKWorldPremium.jp@SD">
    <title lang="en">The "Instruction Manual" Show</title>
    <sub-title lang="en">"Cat"</sub-title>
  </programme>
  <programme start="20260423184500 +0000" stop="20260423193000 +0000" channel="NHKWorldPremium.jp@SD">
    <title lang="ja">あしたが変わるトリセツショー</title>
    <sub-title lang="ja">「ネコ」のトリセツ　科学とヒトと劇場で…</sub-title>
  </programme>
  <programme start="20260423193000 +0000" stop="20260423195800 +0000" channel="NHKWorldPremium.jp@SD">
    <title lang="en">HIMU-BUS! - Pickup Bus Variety Show</title>
  </programme>
  <programme start="20260423193000 +0000" stop="20260423195800 +0000" channel="NHKWorldPremium.jp@SD">
    <title lang="ja">ひむバス！</title>
    <sub-title lang="ja">（41）千葉･南房総市　春満開のお花畑で感謝のサプライス▽高山一実</sub-title>
  </programme>
  <programme start="20260423195800 +0000" stop="20260423200000 +0000" channel="NHKWorldPremium.jp@SD">
    <title lang="en">World Weather</title>
  </programme>
  <programme start="20260423195800 +0000" stop="20260423200000 +0000" channel="NHKWorldPremium.jp@SD">
    <title lang="ja">ワールドウェザー</title>
  </programme>
  <programme start="20260423200000 +0000" stop="20260423201000 +0000" channel="NHKWorldPremium.jp@SD">
    <title lang="en">TV Exercise</title>
  </programme>
  <programme start="20260423200000 +0000" stop="20260423201000 +0000" channel="NHKWorldPremium.jp@SD">
    <title lang="ja">テレビ体操</title>
  </programme>
  <programme start="20260423201000 +0000" stop="20260423202500 +0000" channel="NHKWorldPremium.jp@SD">
    <title lang="en">Health for Today</title>
  </programme>
  <programme start="20260423201000 +0000" stop="20260423202500 +0000" channel="NHKWorldPremium.jp@SD">
    <title lang="ja">きょうの健康</title>
    <sub-title lang="ja">選　ニュース「特定健診の活用術　生活習慣病を防ぐ！」</sub-title>
  </programme>
  <programme start="20260423202500 +0000" stop="20260423205500 +0000" channel="NHKWorldPremium.jp@SD">
    <title lang="en">asaichi on ETV</title>
  </programme>
  <programme start="20260423202500 +0000" stop="20260423205500 +0000" channel="NHKWorldPremium.jp@SD">
    <title lang="ja">Eテレであさイチ</title>
    <sub-title lang="ja">教えて名店さん！（1）極上ポテトサラダ</sub-title>
  </programme>
  <programme start="20260423205500 +0000" stop="20260423210000 +0000" channel="NHKWorldPremium.jp@SD">
    <title lang="en">World Weather</title>
  </programme>
  <programme start="20260423205500 +0000" stop="20260423210000 +0000" channel="NHKWorldPremium.jp@SD">
    <title lang="ja">ワールドウェザー</title>
  </programme>
  <programme start="20260423210000 +0000" stop="20260423220000 +0000" channel="NHKWorldPremium.jp@SD">
    <title lang="en">News: Good Morning, Japan</title>
  </programme>
  <programme start="20260423210000 +0000" stop="20260423220000 +0000" channel="NHKWorldPremium.jp@SD">
    <title lang="ja">NHKニュース おはよう日本（6時台）</title>
  </programme>
  <programme start="20260423220000 +0000" stop="20260423230000 +0000" channel="NHKWorldPremium.jp@SD">
    <title lang="en">News: Good Morning, Japan</title>
  </programme>
  <programme start="20260423220000 +0000" stop="20260423230000 +0000" channel="NHKWorldPremium.jp@SD">
    <title lang="ja">NHKニュース おはよう日本（7時台）</title>
  </programme>
  <programme start="20260423230000 +0000" stop="20260423231500 +0000" channel="NHKWorldPremium.jp@SD">
    <title lang="en">Drama Serial "The Scent of the Wind"</title>
    <sub-title lang="en">Ep. 20</sub-title>
  </programme>
  <programme start="20260423230000 +0000" stop="20260423231500 +0000" channel="NHKWorldPremium.jp@SD">
    <title lang="ja">連続テレビ小説「風、薫る」</title>
    <sub-title lang="ja">（20）</sub-title>
  </programme>
  <programme start="20260423231500 +0000" stop="20260424005400 +0000" channel="NHKWorldPremium.jp@SD">
    <title lang="en">asaichi</title>
  </programme>
  <programme start="20260423231500 +0000" stop="20260424005400 +0000" channel="NHKWorldPremium.jp@SD">
    <title lang="ja">あさイチ</title>
  </programme>
  <programme start="20260424005400 +0000" stop="20260424005500 +0000" channel="NHKWorldPremium.jp@SD">
    <title lang="en">World Weather</title>
  </programme>
  <programme start="20260424005400 +0000" stop="20260424005500 +0000" channel="NHKWorldPremium.jp@SD">
    <title lang="ja">ワールドウェザー</title>
  </programme>
  <programme start="20260424005500 +0000" stop="20260424010000 +0000" channel="NHKWorldPremium.jp@SD">
    <title lang="en">Exercise for Everyone</title>
  </programme>
  <programme start="20260424005500 +0000" stop="20260424010000 +0000" channel="NHKWorldPremium.jp@SD">
    <title lang="ja">みんなの体操</title>
  </programme>
  <programme start="20260424010000 +0000" stop="20260424010500 +0000" channel="NHKWorldPremium.jp@SD">
    <title lang="en">News &amp; Weather</title>
  </programme>
  <programme start="20260424010000 +0000" stop="20260424010500 +0000" channel="NHKWorldPremium.jp@SD">
    <title lang="ja">ニュース・気象情報</title>
  </programme>
  <programme start="20260424010500 +0000" stop="20260424015000 +0000" channel="NHKWorldPremium.jp@SD">
    <title lang="en">Saturday Drama "Mary of Magdalene Restaurant"</title>
    <sub-title lang="en">Ep. 1（New）</sub-title>
  </programme>
  <programme start="20260424010500 +0000" stop="20260424015000 +0000" channel="NHKWorldPremium.jp@SD">
    <title lang="ja">【土曜ドラマ】まぐだら屋のマリア</title>
    <sub-title lang="ja">＜新＞（1）</sub-title>
  </programme>
  <programme start="20260424015000 +0000" stop="20260424015500 +0000" channel="NHKWorldPremium.jp@SD">
    <title lang="en">Mini Program</title>
  </programme>
  <programme start="20260424015000 +0000" stop="20260424015500 +0000" channel="NHKWorldPremium.jp@SD">
    <title lang="ja">ミニ番組</title>
  </programme>
  <programme start="20260424015500 +0000" stop="20260424024000 +0000" channel="NHKWorldPremium.jp@SD">
    <title lang="en">Train Driver's Cab View</title>
  </programme>
  <programme start="20260424015500 +0000" stop="20260424024000 +0000" channel="NHKWorldPremium.jp@SD">
    <title lang="ja">運転席からの風景</title>
    <sub-title lang="ja">桜の記憶</sub-title>
  </programme>
  <programme start="20260424024000 +0000" stop="20260424024500 +0000" channel="NHKWorldPremium.jp@SD">
    <title lang="en">RAMEN JAPAN 5min.</title>
  </programme>
  <programme start="20260424024000 +0000" stop="20260424024500 +0000" channel="NHKWorldPremium.jp@SD">
    <title lang="ja">ラーメンJAPAN 5min.</title>
  </programme>
  <programme start="20260424024500 +0000" stop="20260424025000 +0000" channel="NHKWorldPremium.jp@SD">
    <title lang="en">no art, no life</title>
  </programme>
  <programme start="20260424024500 +0000" stop="20260424025000 +0000" channel="NHKWorldPremium.jp@SD">
    <title lang="ja">no art, no life</title>
  </programme>
  <programme start="20260424025000 +0000" stop="20260424025500 +0000" channel="NHKWorldPremium.jp@SD">
    <title lang="en">Songs for Everyone</title>
  </programme>
  <programme start="20260424025000 +0000" stop="20260424025500 +0000" channel="NHKWorldPremium.jp@SD">
    <title lang="ja">みんなのうた</title>
  </programme>
  <programme start="20260424025500 +0000" stop="20260424030000 +0000" channel="NHKWorldPremium.jp@SD">
    <title lang="en">World Weather</title>
  </programme>
  <programme start="20260424025500 +0000" stop="20260424030000 +0000" channel="NHKWorldPremium.jp@SD">
    <title lang="ja">ワールドウェザー</title>
  </programme>
  <programme start="20260424030000 +0000" stop="20260424032000 +0000" channel="NHKWorldPremium.jp@SD">
    <title lang="en">News</title>
  </programme>
  <programme start="20260424030000 +0000" stop="20260424032000 +0000" channel="NHKWorldPremium.jp@SD">
    <title lang="ja">ニュース</title>
  </programme>
  <programme start="20260424032000 +0000" stop="20260424032500 +0000" channel="NHKWorldPremium.jp@SD">
    <title lang="en">Hello! NHK WORLD-JAPAN</title>
  </programme>
  <programme start="20260424032000 +0000" stop="20260424032500 +0000" channel="NHKWorldPremium.jp@SD">
    <title lang="ja">ハロー！NHKワールドJAPAN</title>
  </programme>
  <programme start="20260424032500 +0000" stop="20260424033000 +0000" channel="NHKWorldPremium.jp@SD">
    <title lang="en">Mini Program</title>
  </programme>
  <programme start="20260424032500 +0000" stop="20260424033000 +0000" channel="NHKWorldPremium.jp@SD">
    <title lang="ja">ミニ番組</title>
  </programme>
  <programme start="20260424033000 +0000" stop="20260424034500 +0000" channel="NHKWorldPremium.jp@SD">
    <title lang="en">Drama Serial "Massan" Encore</title>
    <sub-title lang="en">Ep. 83</sub-title>
  </programme>
  <programme start="20260424033000 +0000" stop="20260424034500 +0000" channel="NHKWorldPremium.jp@SD">
    <title lang="ja">連続テレビ小説・アンコール「マッサン」</title>
    <sub-title lang="ja">（83）</sub-title>
  </programme>
  <programme start="20260424034500 +0000" stop="20260424040000 +0000" channel="NHKWorldPremium.jp@SD">
    <title lang="en">Drama Serial "The Scent of the Wind"</title>
    <sub-title lang="en">Ep. 20</sub-title>
  </programme>
  <programme start="20260424034500 +0000" stop="20260424040000 +0000" channel="NHKWorldPremium.jp@SD">
    <title lang="ja">連続テレビ小説「風、薫る」</title>
    <sub-title lang="ja">（20）</sub-title>
  </programme>
  <programme start="20260424040000 +0000" stop="20260424040500 +0000" channel="NHKWorldPremium.jp@SD">
    <title lang="en">News</title>
  </programme>
  <programme start="20260424040000 +0000" stop="20260424040500 +0000" channel="NHKWorldPremium.jp@SD">
    <title lang="ja">ニュース</title>
  </programme>
  <programme start="20260424040500 +0000" stop="20260424055000 +0000" channel="NHKWorldPremium.jp@SD">
    <title lang="en">News Around Japan</title>
  </programme>
  <programme start="20260424040500 +0000" stop="20260424055000 +0000" channel="NHKWorldPremium.jp@SD">
    <title lang="ja">列島ニュース</title>
  </programme>
  <programme start="20260424055000 +0000" stop="20260424055500 +0000" channel="NHKWorldPremium.jp@SD">
    <title lang="en">World Weather</title>
  </programme>
  <programme start="20260424055000 +0000" stop="20260424055500 +0000" channel="NHKWorldPremium.jp@SD">
    <title lang="ja">ワールドウェザー</title>
  </programme>
  <programme start="20260424055500 +0000" stop="20260424060000 +0000" channel="NHKWorldPremium.jp@SD">
    <title lang="en">Mini Program</title>
  </programme>
  <programme start="20260424055500 +0000" stop="20260424060000 +0000" channel="NHKWorldPremium.jp@SD">
    <title lang="ja">ミニ番組</title>
  </programme>
  <programme start="20260424060000 +0000" stop="20260424061000 +0000" channel="NHKWorldPremium.jp@SD">
    <title lang="en">News &amp; Weather</title>
  </programme>
  <programme start="20260424060000 +0000" stop="20260424061000 +0000" channel="NHKWorldPremium.jp@SD">
    <title lang="ja">ニュース・気象情報</title>
  </programme>
  <programme start="20260424061000 +0000" stop="20260424062500 +0000" channel="NHKWorldPremium.jp@SD">
    <title lang="en">Night Drama Serial "Radio Star"</title>
    <sub-title lang="en">Ep. 15</sub-title>
  </programme>
  <programme start="20260424061000 +0000" stop="20260424062500 +0000" channel="NHKWorldPremium.jp@SD">
    <title lang="ja">【夜ドラ】ラジオスター</title>
    <sub-title lang="ja">（15）</sub-title>
  </programme>
  <programme start="20260424062500 +0000" stop="20260424064000 +0000" channel="NHKWorldPremium.jp@SD">
    <title lang="en">Night Drama Serial "Radio Star"</title>
    <sub-title lang="en">Ep. 16</sub-title>
  </programme>
  <programme start="20260424062500 +0000" stop="20260424064000 +0000" channel="NHKWorldPremium.jp@SD">
    <title lang="ja">【夜ドラ】ラジオスター</title>
    <sub-title lang="ja">（16）</sub-title>
  </programme>
  <programme start="20260424064000 +0000" stop="20260424065000 +0000" channel="NHKWorldPremium.jp@SD">
    <title lang="en">Mimicries--Natural Science for Kids</title>
  </programme>
  <programme start="20260424064000 +0000" stop="20260424065000 +0000" channel="NHKWorldPremium.jp@SD">
    <title lang="ja">ミミクリーズ</title>
  </programme>
  <programme start="20260424065000 +0000" stop="20260424073500 +0000" channel="NHKWorldPremium.jp@SD">
    <title lang="en">Choices on How to Deal with Illness</title>
  </programme>
  <programme start="20260424065000 +0000" stop="20260424073500 +0000" channel="NHKWorldPremium.jp@SD">
    <title lang="ja">チョイス＠病気になったとき</title>
    <sub-title lang="ja">選「中耳炎　薬・手術・最新治療情報」</sub-title>
  </programme>
  <programme start="20260424073500 +0000" stop="20260424080000 +0000" channel="NHKWorldPremium.jp@SD">
    <title lang="en">Exploring Factories</title>
  </programme>
  <programme start="20260424073500 +0000" stop="20260424080000 +0000" channel="NHKWorldPremium.jp@SD">
    <title lang="ja">探検ファクトリー</title>
    <sub-title lang="ja">ウエディングドレス工場　想像を超える細やかな技</sub-title>
  </programme>
  <programme start="20260424080000 +0000" stop="20260424081000 +0000" channel="NHKWorldPremium.jp@SD">
    <title lang="en">PythagoraSwitch</title>
  </programme>
  <programme start="20260424080000 +0000" stop="20260424081000 +0000" channel="NHKWorldPremium.jp@SD">
    <title lang="ja">ピタゴラスイッチ</title>
  </programme>
  <programme start="20260424081000 +0000" stop="20260424082000 +0000" channel="NHKWorldPremium.jp@SD">
    <title lang="en">Blue &amp; Yellow 10min</title>
  </programme>
  <programme start="20260424081000 +0000" stop="20260424082000 +0000" channel="NHKWorldPremium.jp@SD">
    <title lang="ja">あおきいろ</title>
  </programme>
  <programme start="20260424082000 +0000" stop="20260424083500 +0000" channel="NHKWorldPremium.jp@SD">
    <title lang="en">Peek-a-boo</title>
  </programme>
  <programme start="20260424082000 +0000" stop="20260424083500 +0000" channel="NHKWorldPremium.jp@SD">
    <title lang="ja">いないいないばあっ！</title>
  </programme>
  <programme start="20260424083500 +0000" stop="20260424085900 +0000" channel="NHKWorldPremium.jp@SD">
    <title lang="en">With Mother</title>
  </programme>
  <programme start="20260424083500 +0000" stop="20260424085900 +0000" channel="NHKWorldPremium.jp@SD">
    <title lang="ja">おかあさんといっしょ</title>
  </programme>
  <programme start="20260424085900 +0000" stop="20260424090000 +0000" channel="NHKWorldPremium.jp@SD">
    <title lang="en">1-Minute Anime: Songs for SDGs</title>
  </programme>
  <programme start="20260424085900 +0000" stop="20260424090000 +0000" channel="NHKWorldPremium.jp@SD">
    <title lang="ja">SDGsのうた</title>
  </programme>
  <programme start="20260424090000 +0000" stop="20260424091000 +0000" channel="NHKWorldPremium.jp@SD">
    <title lang="en">News</title>
  </programme>
  <programme start="20260424090000 +0000" stop="20260424091000 +0000" channel="NHKWorldPremium.jp@SD">
    <title lang="ja">ニュース</title>
  </programme>
  <programme start="20260424091000 +0000" stop="20260424092500 +0000" channel="NHKWorldPremium.jp@SD">
    <title lang="en">Kid's Discovery</title>
  </programme>
  <programme start="20260424091000 +0000" stop="20260424092500 +0000" channel="NHKWorldPremium.jp@SD">
    <title lang="ja">みいつけた！</title>
  </programme>
  <programme start="20260424092500 +0000" stop="20260424095500 +0000" channel="NHKWorldPremium.jp@SD">
    <title lang="en">Whiz-Kids TV grow</title>
  </programme>
  <programme start="20260424092500 +0000" stop="20260424095500 +0000" channel="NHKWorldPremium.jp@SD">
    <title lang="ja">天才てれびくんgrow</title>
  </programme>
  <programme start="20260424095500 +0000" stop="20260424100000 +0000" channel="NHKWorldPremium.jp@SD">
    <title lang="en">World Weather</title>
  </programme>
  <programme start="20260424095500 +0000" stop="20260424100000 +0000" channel="NHKWorldPremium.jp@SD">
    <title lang="ja">ワールドウェザー</title>
  </programme>
  <programme start="20260424100000 +0000" stop="20260424103000 +0000" channel="NHKWorldPremium.jp@SD">
    <title lang="en">NHK News 7</title>
  </programme>
  <programme start="20260424100000 +0000" stop="20260424103000 +0000" channel="NHKWorldPremium.jp@SD">
    <title lang="ja">NHKニュース7</title>
  </programme>
  <programme start="20260424103000 +0000" stop="20260424105700 +0000" channel="NHKWorldPremium.jp@SD">
    <title lang="en">Tokyo Local Information NETADORI!</title>
  </programme>
  <programme start="20260424103000 +0000" stop="20260424105700 +0000" channel="NHKWorldPremium.jp@SD">
    <title lang="ja">首都圏情報　ネタドリ！</title>
    <sub-title lang="ja">看護師が足りない　医療現場の危機</sub-title>
  </programme>
  <programme start="20260424105700 +0000" stop="20260424114300 +0000" channel="NHKWorldPremium.jp@SD">
    <title lang="en">Trivia Quizzes--You'll Get Scolded by Chiko-chan!</title>
  </programme>
  <programme start="20260424105700 +0000" stop="20260424114300 +0000" channel="NHKWorldPremium.jp@SD">
    <title lang="ja">チコちゃんに叱られる！</title>
    <sub-title lang="ja">▽ちゃんこ鍋の謎▽原宿の謎▽シャンプー容器の謎</sub-title>
  </programme>
  <programme start="20260424114300 +0000" stop="20260424114500 +0000" channel="NHKWorldPremium.jp@SD">
    <title lang="en">World Weather</title>
  </programme>
  <programme start="20260424114300 +0000" stop="20260424114500 +0000" channel="NHKWorldPremium.jp@SD">
    <title lang="ja">ワールドウェザー</title>
  </programme>
  <programme start="20260424114500 +0000" stop="20260424120000 +0000" channel="NHKWorldPremium.jp@SD">
    <title lang="en">NHK News 845</title>
  </programme>
  <programme start="20260424114500 +0000" stop="20260424120000 +0000" channel="NHKWorldPremium.jp@SD">
    <title lang="ja">首都圏ニュース845</title>
  </programme>
  <programme start="20260424120000 +0000" stop="20260424130000 +0000" channel="NHKWorldPremium.jp@SD">
    <title lang="en">News Watch 9</title>
  </programme>
  <programme start="20260424120000 +0000" stop="20260424130000 +0000" channel="NHKWorldPremium.jp@SD">
    <title lang="ja">ニュースウオッチ9</title>
  </programme>
  <programme start="20260424130000 +0000" stop="20260424133000 +0000" channel="NHKWorldPremium.jp@SD">
    <title lang="en">Document 72 Hours</title>
  </programme>
  <programme start="20260424130000 +0000" stop="20260424133000 +0000" channel="NHKWorldPremium.jp@SD">
    <title lang="ja">ドキュメント72時間</title>
    <sub-title lang="ja">春はめぐって　気仙沼・酒屋の物語</sub-title>
  </programme>
  <programme start="20260424133000 +0000" stop="20260424143000 +0000" channel="NHKWorldPremium.jp@SD">
    <title lang="en">Curious World Traveler</title>
    <sub-title lang="en">"Sevilla, Spain"</sub-title>
  </programme>
  <programme start="20260424133000 +0000" stop="20260424143000 +0000" channel="NHKWorldPremium.jp@SD">
    <title lang="ja">世界よくばりトラベラー</title>
    <sub-title lang="ja">スペイン・セビリア</sub-title>
  </programme>
  <programme start="20260424143000 +0000" stop="20260424144000 +0000" channel="NHKWorldPremium.jp@SD">
    <title lang="en">News Commentary</title>
  </programme>
  <programme start="20260424143000 +0000" stop="20260424144000 +0000" channel="NHKWorldPremium.jp@SD">
    <title lang="ja">時論公論</title>
  </programme>
  <programme start="20260424144000 +0000" stop="20260424144500 +0000" channel="NHKWorldPremium.jp@SD">
    <title lang="en">News &amp; Weather</title>
  </programme>
  <programme start="20260424144000 +0000" stop="20260424144500 +0000" channel="NHKWorldPremium.jp@SD">
    <title lang="ja">ニュース・気象情報</title>
  </programme>
  <programme start="20260424144500 +0000" stop="20260424152900 +0000" channel="NHKWorldPremium.jp@SD">
    <title lang="en">International News Report 2026</title>
  </programme>
  <programme start="20260424144500 +0000" stop="20260424152900 +0000" channel="NHKWorldPremium.jp@SD">
    <title lang="ja">国際報道2026</title>
  </programme>
  <programme start="20260424152900 +0000" stop="20260424153000 +0000" channel="NHKWorldPremium.jp@SD">
    <title lang="en">World Weather</title>
  </programme>
  <programme start="20260424152900 +0000" stop="20260424153000 +0000" channel="NHKWorldPremium.jp@SD">
    <title lang="ja">ワールドウェザー</title>
  </programme>
  <programme start="20260424153000 +0000" stop="20260424161300 +0000" channel="NHKWorldPremium.jp@SD">
    <title lang="en">Samurai Drama Selections "Moshichi 2"</title>
    <sub-title lang="en">Ep. 10 (Final)</sub-title>
  </programme>
  <programme start="20260424153000 +0000" stop="20260424161300 +0000" channel="NHKWorldPremium.jp@SD">
    <title lang="ja">【特選！時代劇】茂七の事件簿・新ふしぎ草紙</title>
    <sub-title lang="ja">＜終＞（10）「堪忍箱」</sub-title>
  </programme>
  <programme start="20260424161300 +0000" stop="20260424161500 +0000" channel="NHKWorldPremium.jp@SD">
    <title lang="en">Mini Program</title>
  </programme>
  <programme start="20260424161300 +0000" stop="20260424161500 +0000" channel="NHKWorldPremium.jp@SD">
    <title lang="ja">ミニ番組</title>
  </programme>
  <programme start="20260424161500 +0000" stop="20260424164000 +0000" channel="NHKWorldPremium.jp@SD">
    <title lang="en">My Gardening</title>
  </programme>
  <programme start="20260424161500 +0000" stop="20260424164000 +0000" channel="NHKWorldPremium.jp@SD">
    <title lang="ja">趣味の園芸</title>
    <sub-title lang="ja">ボタン　進化する　“百花の王”</sub-title>
  </programme>
  <programme start="20260424164000 +0000" stop="20260424171000 +0000" channel="NHKWorldPremium.jp@SD">
    <title lang="en">Go Focus</title>
  </programme>
  <programme start="20260424164000 +0000" stop="20260424171000 +0000" channel="NHKWorldPremium.jp@SD">
    <title lang="ja">囲碁フォーカス</title>
  </programme>
  <programme start="20260424171000 +0000" stop="20260424173000 +0000" channel="NHKWorldPremium.jp@SD">
    <title lang="en">Chinese Navi</title>
  </programme>
  <programme start="20260424171000 +0000" stop="20260424173000 +0000" channel="NHKWorldPremium.jp@SD">
    <title lang="ja">中国語！ナビ</title>
    <sub-title lang="ja">（4）</sub-title>
  </programme>
  <programme start="20260424173000 +0000" stop="20260424174000 +0000" channel="NHKWorldPremium.jp@SD">
    <title lang="en">Mimicries--Natural Science for Kids</title>
  </programme>
  <programme start="20260424173000 +0000" stop="20260424174000 +0000" channel="NHKWorldPremium.jp@SD">
    <title lang="ja">ミミクリーズ</title>
  </programme>
  <programme start="20260424174000 +0000" stop="20260424174500 +0000" channel="NHKWorldPremium.jp@SD">
    <title lang="en">World Weather</title>
  </programme>
  <programme start="20260424174000 +0000" stop="20260424174500 +0000" channel="NHKWorldPremium.jp@SD">
    <title lang="ja">ワールドウェザー</title>
  </programme>
  <programme start="20260424174500 +0000" stop="20260424180000 +0000" channel="NHKWorldPremium.jp@SD">
    <title lang="en">Kid's Discovery</title>
  </programme>
  <programme start="20260424174500 +0000" stop="20260424180000 +0000" channel="NHKWorldPremium.jp@SD">
    <title lang="ja">みいつけた！</title>
  </programme>
  <programme start="20260424180000 +0000" stop="20260424182500 +0000" channel="NHKWorldPremium.jp@SD">
    <title lang="en">With Mother</title>
  </programme>
  <programme start="20260424180000 +0000" stop="20260424182500 +0000" channel="NHKWorldPremium.jp@SD">
    <title lang="ja">おかあさんといっしょ</title>
  </programme>
  <programme start="20260424182500 +0000" stop="20260424183000 +0000" channel="NHKWorldPremium.jp@SD">
    <title lang="en">Fun with Okinawa Dialects</title>
  </programme>
  <programme start="20260424182500 +0000" stop="20260424183000 +0000" channel="NHKWorldPremium.jp@SD">
    <title lang="ja">うちなーであそぼ</title>
  </programme>
  <programme start="20260424183000 +0000" stop="20260424184500 +0000" channel="NHKWorldPremium.jp@SD">
    <title lang="en">Drama Serial "The Scent of the Wind"</title>
    <sub-title lang="en">Ep. 20</sub-title>
  </programme>
  <programme start="20260424183000 +0000" stop="20260424184500 +0000" channel="NHKWorldPremium.jp@SD">
    <title lang="ja">連続テレビ小説「風、薫る」</title>
    <sub-title lang="ja">（20）</sub-title>
  </programme>
  <programme start="20260424184500 +0000" stop="20260424193000 +0000" channel="NHKWorldPremium.jp@SD">
    <title lang="en">Saturday Drama "Mary of Magdalene Restaurant"</title>
    <sub-title lang="en">Ep. 1（New）</sub-title>
  </programme>
  <programme start="20260424184500 +0000" stop="20260424193000 +0000" channel="NHKWorldPremium.jp@SD">
    <title lang="ja">【土曜ドラマ】まぐだら屋のマリア</title>
    <sub-title lang="ja">＜新＞（1）</sub-title>
  </programme>
  <programme start="20260424193000 +0000" stop="20260424193500 +0000" channel="NHKWorldPremium.jp@SD">
    <title lang="en">World's Magnificent Sight Journey</title>
  </programme>
  <programme start="20260424193000 +0000" stop="20260424193500 +0000" channel="NHKWorldPremium.jp@SD">
    <title lang="ja">巡る世界絶景</title>
  </programme>
  <programme start="20260424193500 +0000" stop="20260424195800 +0000" channel="NHKWorldPremium.jp@SD">
    <title lang="en">Delicious Japan!</title>
  </programme>
  <programme start="20260424193500 +0000" stop="20260424195800 +0000" channel="NHKWorldPremium.jp@SD">
    <title lang="ja">うまいッ！</title>
    <sub-title lang="ja">爆走するにわとりが産む！極上の卵～鹿児島　霧島市～</sub-title>
  </programme>
  <programme start="20260424195800 +0000" stop="20260424200000 +0000" channel="NHKWorldPremium.jp@SD">
    <title lang="en">World Weather</title>
  </programme>
  <programme start="20260424195800 +0000" stop="20260424200000 +0000" channel="NHKWorldPremium.jp@SD">
    <title lang="ja">ワールドウェザー</title>
  </programme>
  <programme start="20260424200000 +0000" stop="20260424201000 +0000" channel="NHKWorldPremium.jp@SD">
    <title lang="en">TV Exercise</title>
  </programme>
  <programme start="20260424200000 +0000" stop="20260424201000 +0000" channel="NHKWorldPremium.jp@SD">
    <title lang="ja">テレビ体操</title>
  </programme>
  <programme start="20260424201000 +0000" stop="20260424202500 +0000" channel="NHKWorldPremium.jp@SD">
    <title lang="en">Natural Grandeur of the East</title>
  </programme>
  <programme start="20260424201000 +0000" stop="20260424202500 +0000" channel="NHKWorldPremium.jp@SD">
    <title lang="ja">さわやか自然百景</title>
    <sub-title lang="ja">選　鹿児島　沖永良部島の海</sub-title>
  </programme>
  <programme start="20260424202500 +0000" stop="20260424205000 +0000" channel="NHKWorldPremium.jp@SD">
    <title lang="en">NHK Regional Showcases: Wind of Kumamoto</title>
  </programme>
  <programme start="20260424202500 +0000" stop="20260424205000 +0000" channel="NHKWorldPremium.jp@SD">
    <title lang="ja">【NHK地域局発】 くまもとの風</title>
    <sub-title lang="ja">あの経験を、未来に生かす～熊本地震10年　現場からの教訓～</sub-title>
  </programme>
  <programme start="20260424205000 +0000" stop="20260424205500 +0000" channel="NHKWorldPremium.jp@SD">
    <title lang="en">Mini Program</title>
  </programme>
  <programme start="20260424205000 +0000" stop="20260424205500 +0000" channel="NHKWorldPremium.jp@SD">
    <title lang="ja">ミニ番組</title>
  </programme>
  <programme start="20260424205500 +0000" stop="20260424210000 +0000" channel="NHKWorldPremium.jp@SD">
    <title lang="en">World Weather</title>
  </programme>
  <programme start="20260424205500 +0000" stop="20260424210000 +0000" channel="NHKWorldPremium.jp@SD">
    <title lang="ja">ワールドウェザー</title>
  </programme>
  <programme start="20260424210000 +0000" stop="20260424220000 +0000" channel="NHKWorldPremium.jp@SD">
    <title lang="en">News: Good Morning, Japan</title>
  </programme>
  <programme start="20260424210000 +0000" stop="20260424220000 +0000" channel="NHKWorldPremium.jp@SD">
    <title lang="ja">NHKニュース おはよう日本（6時台）</title>
  </programme>
  <programme start="20260424220000 +0000" stop="20260424225900 +0000" channel="NHKWorldPremium.jp@SD">
    <title lang="en">News: Good Morning, Japan</title>
  </programme>
  <programme start="20260424220000 +0000" stop="20260424225900 +0000" channel="NHKWorldPremium.jp@SD">
    <title lang="ja">NHKニュース おはよう日本（7時台）</title>
  </programme>
  <programme start="20260424225900 +0000" stop="20260424230000 +0000" channel="NHKWorldPremium.jp@SD">
    <title lang="en">World Weather</title>
  </programme>
  <programme start="20260424225900 +0000" stop="20260424230000 +0000" channel="NHKWorldPremium.jp@SD">
    <title lang="ja">ワールドウェザー</title>
  </programme>
  <programme start="20260424230000 +0000" stop="20260424231500 +0000" channel="NHKWorldPremium.jp@SD">
    <title lang="en">Drama Serial "The Scent of the Wind"</title>
    <sub-title lang="en">Week 4</sub-title>
  </programme>
  <programme start="20260424230000 +0000" stop="20260424231500 +0000" channel="NHKWorldPremium.jp@SD">
    <title lang="ja">連続テレビ小説「風、薫る」</title>
    <sub-title lang="ja">第4週</sub-title>
  </programme>
  <programme start="20260424231500 +0000" stop="20260425000000 +0000" channel="NHKWorldPremium.jp@SD">
    <title lang="en">Trivia Quizzes--You'll Get Scolded by Chiko-chan!</title>
  </programme>
  <programme start="20260424231500 +0000" stop="20260425000000 +0000" channel="NHKWorldPremium.jp@SD">
    <title lang="ja">チコちゃんに叱られる！</title>
    <sub-title lang="ja">▽ちゃんこ鍋の謎▽原宿の謎▽シャンプー容器の謎</sub-title>
  </programme>
  <programme start="20260425000000 +0000" stop="20260425002800 +0000" channel="NHKWorldPremium.jp@SD">
    <title lang="en">Darwin's Amazing Animals</title>
    <sub-title lang="en">"The Mysterious White Sea Animals"</sub-title>
  </programme>
  <programme start="20260425000000 +0000" stop="20260425002800 +0000" channel="NHKWorldPremium.jp@SD">
    <title lang="ja">ダーウィンが来た！</title>
    <sub-title lang="ja">「生きもの大集合！謎の白い海」</sub-title>
  </programme>
  <programme start="20260425002800 +0000" stop="20260425003000 +0000" channel="NHKWorldPremium.jp@SD">
    <title lang="en">Mini Program</title>
  </programme>
  <programme start="20260425002800 +0000" stop="20260425003000 +0000" channel="NHKWorldPremium.jp@SD">
    <title lang="ja">ミニ番組</title>
  </programme>
  <programme start="20260425003000 +0000" stop="20260425010000 +0000" channel="NHKWorldPremium.jp@SD">
    <title lang="en">Document 72 Hours</title>
  </programme>
  <programme start="20260425003000 +0000" stop="20260425010000 +0000" channel="NHKWorldPremium.jp@SD">
    <title lang="ja">ドキュメント72時間</title>
    <sub-title lang="ja">池袋“チャイナタウン”のフードコート</sub-title>
  </programme>
  <programme start="20260425010000 +0000" stop="20260425010500 +0000" channel="NHKWorldPremium.jp@SD">
    <title lang="en">News &amp; Weather</title>
  </programme>
  <programme start="20260425010000 +0000" stop="20260425010500 +0000" channel="NHKWorldPremium.jp@SD">
    <title lang="ja">ニュース・気象情報</title>
  </programme>
  <programme start="20260425010500 +0000" stop="20260425013300 +0000" channel="NHKWorldPremium.jp@SD">
    <title lang="en">HIMU-BUS! - Pickup Bus Variety Show</title>
  </programme>
  <programme start="20260425010500 +0000" stop="20260425013300 +0000" channel="NHKWorldPremium.jp@SD">
    <title lang="ja">ひむバス！</title>
    <sub-title lang="ja">（41）千葉･南房総市　春満開のお花畑で感謝のサプライス▽高山一実</sub-title>
  </programme>
  <programme start="20260425013300 +0000" stop="20260425020300 +0000" channel="NHKWorldPremium.jp@SD">
    <title lang="en">SCIENCE ZERO</title>
  </programme>
  <programme start="20260425013300 +0000" stop="20260425020300 +0000" channel="NHKWorldPremium.jp@SD">
    <title lang="ja">サイエンスZERO</title>
    <sub-title lang="ja">アニメ世界に科学で迫る！どら焼きでロボットは動くのか？</sub-title>
  </programme>
  <programme start="20260425020300 +0000" stop="20260425020600 +0000" channel="NHKWorldPremium.jp@SD">
    <title lang="en">Mini Program</title>
  </programme>
  <programme start="20260425020300 +0000" stop="20260425020600 +0000" channel="NHKWorldPremium.jp@SD">
    <title lang="ja">ミニ番組</title>
  </programme>
  <programme start="20260425020600 +0000" stop="20260425023000 +0000" channel="NHKWorldPremium.jp@SD">
    <title lang="en">Delicious Japan!</title>
  </programme>
  <programme start="20260425020600 +0000" stop="20260425023000 +0000" channel="NHKWorldPremium.jp@SD">
    <title lang="ja">うまいッ！</title>
    <sub-title lang="ja">“いっぺー”甘い！ 完熟かぼちゃ～沖縄・南風原町～</sub-title>
  </programme>
  <programme start="20260425023000 +0000" stop="20260425025000 +0000" channel="NHKWorldPremium.jp@SD">
    <title lang="en">Documentary: 20 Minutes</title>
  </programme>
  <programme start="20260425023000 +0000" stop="20260425025000 +0000" channel="NHKWorldPremium.jp@SD">
    <title lang="ja">ドキュメント20min.</title>
    <sub-title lang="ja">ポーカーという人生</sub-title>
  </programme>
  <programme start="20260425025000 +0000" stop="20260425025600 +0000" channel="NHKWorldPremium.jp@SD">
    <title lang="en">Songs for Everyone</title>
  </programme>
  <programme start="20260425025000 +0000" stop="20260425025600 +0000" channel="NHKWorldPremium.jp@SD">
    <title lang="ja">みんなのうた</title>
  </programme>
  <programme start="20260425025600 +0000" stop="20260425030000 +0000" channel="NHKWorldPremium.jp@SD">
    <title lang="en">World Weather</title>
  </programme>
  <programme start="20260425025600 +0000" stop="20260425030000 +0000" channel="NHKWorldPremium.jp@SD">
    <title lang="ja">ワールドウェザー</title>
  </programme>
  <programme start="20260425030000 +0000" stop="20260425031500 +0000" channel="NHKWorldPremium.jp@SD">
    <title lang="en">News</title>
  </programme>
  <programme start="20260425030000 +0000" stop="20260425031500 +0000" channel="NHKWorldPremium.jp@SD">
    <title lang="ja">ニュース</title>
  </programme>
  <programme start="20260425031500 +0000" stop="20260425034000 +0000" channel="NHKWorldPremium.jp@SD">
    <title lang="en">NHK Regional Showcases: Wind of Kumamoto</title>
  </programme>
  <programme start="20260425031500 +0000" stop="20260425034000 +0000" channel="NHKWorldPremium.jp@SD">
    <title lang="ja">【NHK地域局発】 くまもとの風</title>
    <sub-title lang="ja">あの経験を、未来に生かす～熊本地震10年　現場からの教訓～</sub-title>
  </programme>
  <programme start="20260425034000 +0000" stop="20260425034500 +0000" channel="NHKWorldPremium.jp@SD">
    <title lang="en">Fun with Okinawa Dialects</title>
  </programme>
  <programme start="20260425034000 +0000" stop="20260425034500 +0000" channel="NHKWorldPremium.jp@SD">
    <title lang="ja">うちなーであそぼ</title>
  </programme>
  <programme start="20260425034500 +0000" stop="20260425040000 +0000" channel="NHKWorldPremium.jp@SD">
    <title lang="en">Drama Serial "The Scent of the Wind"</title>
    <sub-title lang="en">Week 4</sub-title>
  </programme>
  <programme start="20260425034500 +0000" stop="20260425040000 +0000" channel="NHKWorldPremium.jp@SD">
    <title lang="ja">連続テレビ小説「風、薫る」</title>
    <sub-title lang="ja">第4週</sub-title>
  </programme>
  <programme start="20260425040000 +0000" stop="20260425040500 +0000" channel="NHKWorldPremium.jp@SD">
    <title lang="en">News &amp; Weather</title>
  </programme>
  <programme start="20260425040000 +0000" stop="20260425040500 +0000" channel="NHKWorldPremium.jp@SD">
    <title lang="ja">ニュース・気象情報</title>
  </programme>
  <programme start="20260425040500 +0000" stop="20260425045000 +0000" channel="NHKWorldPremium.jp@SD">
    <title lang="en">Historical Drama "BROTHERS IN ARMS"</title>
    <sub-title lang="en">Ep. 15</sub-title>
  </programme>
  <programme start="20260425040500 +0000" stop="20260425045000 +0000" channel="NHKWorldPremium.jp@SD">
    <title lang="ja">大河ドラマ「豊臣兄弟！」</title>
    <sub-title lang="ja">（15）姉川大合戦</sub-title>
  </programme>
  <programme start="20260425045000 +0000" stop="20260425052000 +0000" channel="NHKWorldPremium.jp@SD">
    <title lang="en">Yumi's Handmade Life in the Winter Mountains</title>
  </programme>
  <programme start="20260425045000 +0000" stop="20260425052000 +0000" channel="NHKWorldPremium.jp@SD">
    <title lang="ja">ユミさんの手づくり山暮らし、冬</title>
  </programme>
  <programme start="20260425052000 +0000" stop="20260425060500 +0000" channel="NHKWorldPremium.jp@SD">
    <title lang="en">Train Driver's Cab View</title>
  </programme>
  <programme start="20260425052000 +0000" stop="20260425060500 +0000" channel="NHKWorldPremium.jp@SD">
    <title lang="ja">運転席からの風景</title>
    <sub-title lang="ja">桜の記憶</sub-title>
  </programme>
  <programme start="20260425060500 +0000" stop="20260425073500 +0000" channel="NHKWorldPremium.jp@SD">
    <title lang="en">Amazing Disassembly Works</title>
    <sub-title lang="en">"EXPO 2025 Osaka"</sub-title>
  </programme>
  <programme start="20260425060500 +0000" stop="20260425073500 +0000" channel="NHKWorldPremium.jp@SD">
    <title lang="ja">解体キングダム</title>
    <sub-title lang="ja">大阪・関西万博スペシャル</sub-title>
  </programme>
  <programme start="20260425073500 +0000" stop="20260425080000 +0000" channel="NHKWorldPremium.jp@SD">
    <title lang="en">NHK Regional Showcases: Wind of Kumamoto</title>
  </programme>
  <programme start="20260425073500 +0000" stop="20260425080000 +0000" channel="NHKWorldPremium.jp@SD">
    <title lang="ja">【NHK地域局発】 くまもとの風</title>
    <sub-title lang="ja">あの経験を、未来に生かす～熊本地震10年　現場からの教訓～</sub-title>
  </programme>
  <programme start="20260425080000 +0000" stop="20260425083000 +0000" channel="NHKWorldPremium.jp@SD">
    <title lang="en">Peek-a-boo Wan Wan Wonderland</title>
  </programme>
  <programme start="20260425080000 +0000" stop="20260425083000 +0000" channel="NHKWorldPremium.jp@SD">
    <title lang="ja">ワンワンわんだーらんど</title>
  </programme>
  <programme start="20260425083000 +0000" stop="20260425083500 +0000" channel="NHKWorldPremium.jp@SD">
    <title lang="en">Songs for Everyone</title>
  </programme>
  <programme start="20260425083000 +0000" stop="20260425083500 +0000" channel="NHKWorldPremium.jp@SD">
    <title lang="ja">みんなのうた</title>
  </programme>
  <programme start="20260425083500 +0000" stop="20260425085900 +0000" channel="NHKWorldPremium.jp@SD">
    <title lang="en">With Mother</title>
  </programme>
  <programme start="20260425083500 +0000" stop="20260425085900 +0000" channel="NHKWorldPremium.jp@SD">
    <title lang="ja">おかあさんといっしょ</title>
  </programme>
  <programme start="20260425085900 +0000" stop="20260425090000 +0000" channel="NHKWorldPremium.jp@SD">
    <title lang="en">1-Minute Anime: Songs for SDGs</title>
  </programme>
  <programme start="20260425085900 +0000" stop="20260425090000 +0000" channel="NHKWorldPremium.jp@SD">
    <title lang="ja">SDGsのうた</title>
  </programme>
  <programme start="20260425090000 +0000" stop="20260425090500 +0000" channel="NHKWorldPremium.jp@SD">
    <title lang="en">News</title>
  </programme>
  <programme start="20260425090000 +0000" stop="20260425090500 +0000" channel="NHKWorldPremium.jp@SD">
    <title lang="ja">ニュース</title>
  </programme>
  <programme start="20260425090500 +0000" stop="20260425093500 +0000" channel="NHKWorldPremium.jp@SD">
    <title lang="en">Tokoro-san's Pursuit of Truth</title>
  </programme>
  <programme start="20260425090500 +0000" stop="20260425093500 +0000" channel="NHKWorldPremium.jp@SD">
    <title lang="ja">所さん！事件ですよ</title>
    <sub-title lang="ja">選　150万円の“安眠の館”にセレブが殺到！？</sub-title>
  </programme>
  <programme start="20260425093500 +0000" stop="20260425094500 +0000" channel="NHKWorldPremium.jp@SD">
    <title lang="en">Fun with Japanese</title>
  </programme>
  <programme start="20260425093500 +0000" stop="20260425094500 +0000" channel="NHKWorldPremium.jp@SD">
    <title lang="ja">にほんごであそぼ</title>
  </programme>
  <programme start="20260425094500 +0000" stop="20260425095500 +0000" channel="NHKWorldPremium.jp@SD">
    <title lang="en">Let's Enjoy English and Meets the World</title>
  </programme>
  <programme start="20260425094500 +0000" stop="20260425095500 +0000" channel="NHKWorldPremium.jp@SD">
    <title lang="ja">えいごであそぼ Meets the World</title>
  </programme>
  <programme start="20260425095500 +0000" stop="20260425100000 +0000" channel="NHKWorldPremium.jp@SD">
    <title lang="en">World Weather</title>
  </programme>
  <programme start="20260425095500 +0000" stop="20260425100000 +0000" channel="NHKWorldPremium.jp@SD">
    <title lang="ja">ワールドウェザー</title>
  </programme>
  <programme start="20260425100000 +0000" stop="20260425103000 +0000" channel="NHKWorldPremium.jp@SD">
    <title lang="en">NHK News 7</title>
  </programme>
  <programme start="20260425100000 +0000" stop="20260425103000 +0000" channel="NHKWorldPremium.jp@SD">
    <title lang="ja">NHKニュース7</title>
  </programme>
  <programme start="20260425103000 +0000" stop="20260425110700 +0000" channel="NHKWorldPremium.jp@SD">
    <title lang="en">Strolling with Tamori</title>
  </programme>
  <programme start="20260425103000 +0000" stop="20260425110700 +0000" channel="NHKWorldPremium.jp@SD">
    <title lang="ja">ブラタモリ</title>
    <sub-title lang="ja">国宝犬山城▼天下人が愛した城の秘密？タモリ、国宝五城制覇へ！</sub-title>
  </programme>
  <programme start="20260425110700 +0000" stop="20260425115300 +0000" channel="NHKWorldPremium.jp@SD">
    <title lang="en">Project X: The Challengers-New Beginnings</title>
    <sub-title lang="en">"Roasted Sweet Potato"</sub-title>
  </programme>
  <programme start="20260425110700 +0000" stop="20260425115300 +0000" channel="NHKWorldPremium.jp@SD">
    <title lang="ja">新プロジェクトX ～挑戦者たち～</title>
    <sub-title lang="ja">“たかが芋”とは言わせない　執念の逆転劇～焼き芋～</sub-title>
  </programme>
  <programme start="20260425115300 +0000" stop="20260425115500 +0000" channel="NHKWorldPremium.jp@SD">
    <title lang="en">World Weather</title>
  </programme>
  <programme start="20260425115300 +0000" stop="20260425115500 +0000" channel="NHKWorldPremium.jp@SD">
    <title lang="ja">ワールドウェザー</title>
  </programme>
  <programme start="20260425115500 +0000" stop="20260425120000 +0000" channel="NHKWorldPremium.jp@SD">
    <title lang="en">News &amp; Weather</title>
  </programme>
  <programme start="20260425115500 +0000" stop="20260425120000 +0000" channel="NHKWorldPremium.jp@SD">
    <title lang="ja">ニュース・気象情報</title>
  </programme>
  <programme start="20260425120000 +0000" stop="20260425130000 +0000" channel="NHKWorldPremium.jp@SD">
    <title lang="en">Saturday Watch 9</title>
  </programme>
  <programme start="20260425120000 +0000" stop="20260425130000 +0000" channel="NHKWorldPremium.jp@SD">
    <title lang="ja">サタデーウオッチ9</title>
  </programme>
  <programme start="20260425130000 +0000" stop="20260425134500 +0000" channel="NHKWorldPremium.jp@SD">
    <title lang="en">Saturday Drama "Mary of Magdalene Restaurant"</title>
    <sub-title lang="en">Ep. 2</sub-title>
  </programme>
  <programme start="20260425130000 +0000" stop="20260425134500 +0000" channel="NHKWorldPremium.jp@SD">
    <title lang="ja">【土曜ドラマ】まぐだら屋のマリア</title>
    <sub-title lang="ja">（2）</sub-title>
  </programme>
  <programme start="20260425134500 +0000" stop="20260425134900 +0000" channel="NHKWorldPremium.jp@SD">
    <title lang="en">Mini Program</title>
  </programme>
  <programme start="20260425134500 +0000" stop="20260425134900 +0000" channel="NHKWorldPremium.jp@SD">
    <title lang="ja">ミニ番組</title>
  </programme>
  <programme start="20260425134900 +0000" stop="20260425135500 +0000" channel="NHKWorldPremium.jp@SD">
    <title lang="en">Japan Genesis: Pilgrimage to the Land of the Gods 5min.</title>
  </programme>
  <programme start="20260425134900 +0000" stop="20260425135500 +0000" channel="NHKWorldPremium.jp@SD">
    <title lang="ja">ニッポン創世　神々の道をたどる　5min.</title>
  </programme>
  <programme start="20260425135500 +0000" stop="20260425140000 +0000" channel="NHKWorldPremium.jp@SD">
    <title lang="en">News &amp; Weather</title>
  </programme>
  <programme start="20260425135500 +0000" stop="20260425140000 +0000" channel="NHKWorldPremium.jp@SD">
    <title lang="ja">ニュース・気象情報</title>
  </programme>
  <programme start="20260425140000 +0000" stop="20260425143000 +0000" channel="NHKWorldPremium.jp@SD">
    <title lang="en">Venue101</title>
  </programme>
  <programme start="20260425140000 +0000" stop="20260425143000 +0000" channel="NHKWorldPremium.jp@SD">
    <title lang="ja">Venue101</title>
    <sub-title lang="ja">Ayumu Imazu・にしな・HANA・Number_i</sub-title>
  </programme>
  <programme start="20260425143000 +0000" stop="20260425160000 +0000" channel="NHKWorldPremium.jp@SD">
    <title lang="en">Sada Masashi's Midnight Talk Show</title>
  </programme>
  <programme start="20260425143000 +0000" stop="20260425160000 +0000" channel="NHKWorldPremium.jp@SD">
    <title lang="ja">今夜も生でさだまさし</title>
    <sub-title lang="ja">鳥取サキューベリーマッチ</sub-title>
  </programme>
</tv>